<?xml version="1.0" encoding="UTF-8"?><compiereTrl language="es_EC" table="AD_WF_NODE"><row id="106" trl="N"><value column="Name" original="Project Reporting">Información del proyecto</value><value column="Description" original="Maintain Project Reporting Cycles">Mantenimiento de los ciclos de reporting de proyectos</value><value column="Help" original="The Project Cycle Window defines the steps associated with a specific Project.You may want to define several Project cycles to differentiate the different types of projects. Project cycles may use all or a subset of the used Project Status (e.g. Your opportunity project cycle may include the steps from prospect to contract - the service cycle may include steps from installation to customer acceptance.">La ventana de los ciclos de reporting de proyectos define los pasos asociados a un Proyecto determinado. El usuario puede definir diferentes ciclos para diferenciar tipos de proyecto diferentes.</value></row><row id="107" trl="N"><value column="Name" original="Language">Idioma</value><value column="Description" original="Maintain Languages">Mantenimiento de idiomas</value><value column="Help" original="The Language Window allows you to define multiple parallel language for users. This allows users to access the same data but have the windows, tabs and fields appear in different languages.If a language is a System Language, you can change the User Interface to this language (after translation).  Otherwise the language is only used for printing documents.&#10;&#13;For the language code, we suggest using the Java convention of country and language (e.g. fr_CN - Canadian French).&#10;&#13;Verify the translation creates missing translation records. Start this process after creating a new language.">&lt;P&gt;La ventana Idioma permite definir úultiples idiomas para los usuarios simultáneamente. Por ello, es posible que diferenes usuarios accedan a la aplicación y trabajen con la misma información pero con interfaces (ventanas, solapas y campos) en diferentes idiomas.&amp;nbsp;&lt;/P&gt;
&#13;&lt;P&gt;Si el&amp;nbsp;idioma es Lenguaje del sistema, se permite la traducción de los&amp;nbsp;campos de las pantallas. Sino, únicamente se utilizará dicho idioma para impresión de informes.&lt;/P&gt;
&#13;&lt;P&gt;Para la codificación de cada idioma, se sugiere utilizar las especificaciones para lenguas y países desarrollada por Java. Por ejemplo: fr_CN - Francés de Canadá. &lt;/P&gt;</value></row><row id="108" trl="N"><value column="Name" original="Project Type">Tipo de proyecto</value><value column="Description" original="Maintain Project Type and Phase">Mantenimiento de los tipos y fases de un proyecto</value><value column="Help" original="Maintain Project Types and their Phases with standard performance information">La ventana de Tipo de proyecto permite mantener la tipología de proyectos y sus fases con la información del performance estándar.</value></row><row id="110" trl="N"><value column="Name" original="Client">Entidad</value><value column="Description" original="Maintain Clients">Mantenimiento de clientes</value><value column="Help" original="The Client is the highest level of an independent business entity.  Each Client will have one or more Organizations reporting to it.  Each Client defines the accounting parameters (Accounting Schema, Tree definition, Non Monetary UOM's).Do not create a new client in this window, but use &quot;Initial Client Setup&quot; to set up the required security and access rules. If you create a new client here, you will not be able to view it and also the required client infrastructure would not have been set up.">Entidad es la unidad de más alto rango. Cada entidad puede estar formada por una o más organizaciones. 
&#13;Cada entidad define unos parametros de contabilidad.&lt;br&gt;
&#13;
&#13;No crear nuevas entidades mediante esta ventana, porque esta no será visible desde otras pantallas y el proceso de creación de una nueva entidad no habrá sido ejecutado.
&#13;&lt;br&gt;Para la creación de una nueva ventana ejecute el proceso "Reglas generales / Reglas de entidad / Crear entidad". 
&#13;
&#13;</value></row><row id="111" trl="N"><value column="Name" original="Role">Rol</value><value column="Description" original="Maintain User Responsibilities">Mantenimiento de roles</value><value column="Help" original="The Role Window allows you to define the different roles that users of this system will have.  Roles control access to windows, tasks, reports, etc. For a client an Administrator and User role are predefined. You may add additional roles to control access for specific functionality or data.You can add users to the role.">&lt;P&gt;La ventana de&amp;nbsp;Roles&amp;nbsp;permite&amp;nbsp;definir los "papeles" o&amp;nbsp;"status"&amp;nbsp;para&amp;nbsp;cada uno de los usuarios de este sistema. Los roles controlan el acceso a las ventanas, tareas, informes, etc.&lt;/P&gt;
&#13;&lt;P&gt;Para cada entidad los roles de Administrador y Usuario están predefinidos. Además se pueden añadir&amp;nbsp;roles adicionales para controlar el acceso a las diferentes funcionalidades o datos. &lt;/P&gt;
&#13;&lt;P&gt;Posteriormente, a cada usuario se le puede&amp;nbsp;asignar uno o más&amp;nbsp;roles.&lt;/P&gt;</value></row><row id="112" trl="N"><value column="Name" original="User">Usuario</value><value column="Description" original="Maintain Users of the system">Mantenimiento de los usuarios del sistema</value><value column="Help" original="The User Window allows you to define each User of the system.  Users can log into the system and have access to functionality via one or more roles.">La ventana Usuario permite definir y editar usuarios de la aplicación. Una vez han accedido a la aplicación, dependiendo de los roles que cada usuario tenga asignados podrá acceder a unas funcionalidades determinadas. A cada usuario se le pueden asignar uno o varios roles.
&#13;</value></row><row id="113" trl="N"><value column="Name" original="Organization">Organización</value><value column="Description" original="Maintain Organizations">Mantenimiento de las organizaciones</value><value column="Help" original="The Organization Window allows you to define and maintain Organizational entities.  An Organization is often a legal entity or sub-unit for which documents and transactions are processed">La ventana de Organización permite crear nuevas organizaciones para una&amp;nbsp; entidad particular. Se entiende por organización cada una de las divisiones de una entidad, sea realizada por objetivos, localización,...</value></row><row id="114" trl="N"><value column="Name" original="Project (Service)">Proyecto(servicios)</value><value column="Description" original="Maintain Service Projects">Mantenimiento de los proyectos de servicio</value><value column="Help" original="The Project Window is used to define the projects which will be tracked via documents.">La ventana de Proyectos se usa para definir los proyectos que se controlaran via documentos.</value></row><row id="115" trl="N"><value column="Name" original="Project Status Report">Estado de proyecto</value><value column="Description" original="Summary and detail Project Status">Resumen y detalles del estado del projecto.</value><value column="Help" original="To report on your projects, select the project cycle and restricting parameters.&#10;If you miss certain projects check their status and if the project status is included in your Project cycle.">Para introducir información de los projectos, seleccionar el ciclo del projecto y los parametros restrictivos.</value></row><row id="116" trl="N"><value column="Name" original="Accounting Schema">Esquema de contabilidad</value><value column="Description" original="Project as Account Segment"></value><value column="Help" original="To enable accounting reporting of projects, create and enable a project segment in the account elements."></value></row><row id="118" trl="Y"><value column="Name" original="System Elements">Elementos del sistema</value><value column="Description" original="Translate System Elements">Traducción de los elementos del sistema.</value><value column="Help" original="System Elements are used to centrally define field labels, description and help. When translating an Element, the appropriate information of Fields in Windows, Parameters and Reports are translated (overwritten)">Los elementos del sistema permiten definir de manera centralizada las etiquetas de los campos, descripciones y ayudas. Al modificar un elemento del sistema, cada uno de los campos de la aplicación enlazado con este elemento es sobreescrito.</value></row><row id="119" trl="Y"><value column="Name" original="Messages">Mensajes</value><value column="Description" original="Translate Messages">Traducción de mensajes</value><value column="Help" original="Translate the messages used in Windows, Forms and Processes">Traducción de los mensajes utilizados en las ventanas, formularios y procesos.</value></row><row id="120" trl="Y"><value column="Name" original="Reference">Referencia</value><value column="Description" original="Translate References">Traducción de referencias.</value><value column="Help" original="References are used as prefedined selection lists.  You only need to translate the List Elements !!">Las referencias se utilizan como valores por defecto para las listas de selección. Es suficiente con traducir los elementos de la lista.</value></row><row id="121" trl="N"><value column="Name" original="Window &amp; Tab">Ventanas y solapas</value><value column="Description" original="Translate Windows and Tabs">Traducción de ventanas y solapas</value><value column="Help" original="Translate the Name, Description and Help for Windows and Tabs.  Most of the Fields are already translated, if they are centrally maintained.">Permite traducir el nombre, la descripción y la ayuda de las ventanas y las solapas de la aplicación. La mayoría de los campos de la aplicación se actualizan con la modificación de los elementos.</value></row><row id="122" trl="Y"><value column="Name" original="Form">Fomulario</value><value column="Description" original="Translate Forms">Traducción de los formularios.</value><value column="Help" original="Forms are special Windows and you need to translate its name, description and Help.">Los formularios son ventanas especiales que requieren la traducción de su nombre, descripción y ayuda.</value></row><row id="123" trl="Y"><value column="Name" original="Report &amp; Process">Informes y procesos</value><value column="Description" original="Translate Reports and Processes.">Traducción de informes y procesos.</value><value column="Help" original="Translate the Name, Description and Help for Processes and Reports. You don't need to translate the Parameters, if they are centrally maintained.">Traducir el nombre, descripción y ayuda de los procesos y los informes. No es necesaria la traducción los parametros centralizados.&#13;
</value></row><row id="125" trl="N"><value column="Name" original="Calendar Year and Period">Calendario anual y periodos</value><value column="Description" original="Maintain Calendars Years Periods">Mantenimiento de los periodos del calendario anual</value><value column="Help" original="The Calendar Year and Periods defines the calendars that will be used for period control and reporting. You can also define non-standard calendars (e.g. business year from July to June).">El Calendario anual y periodos permite crear el calendario contable.  Además, es posible definir calendarios no estandar. Por ejemplo, calendarios que comiencen en junio y acaben en Mayo.</value></row><row id="126" trl="N"><value column="Name" original="Account Element">Elemento de la cuenta</value><value column="Description" original="Maintain Account Elements">Mantenimiento de los elementos de la cuenta</value><value column="Help" original="The Account Element Window is used to define and maintain the Accounting Element and User Defined Elements. One of the account segments is your natural account segment (Chart of Account). You may add a new account element for parallel reporting or for user defined accounting segments. ">La ventana de Elementos de contabilidad se utiliza para configurar las cuentas contables de la organización. Una organización permite tener varios elementos contables. De modo que pueda llevarse dos contabilidades en diferentes paises sobre la misma gestión. Y en cada elemento contable se configuran los valores del elemento. Los valores del elemento son las cuentas contables. De este modo en la solapa Valor del Elemento, en modo relación, se muestran todas las cuentas contables existentes. Para la creación de una nueva cuenta contable, una vez creado el registro (activo, pasivo, etc. Epigrafe, desglose,cuenta, subcuenta), se debe de acceder al árbol contable y configurar el nuevo registro en el lugar adecuado del árbol.</value></row><row id="127" trl="N"><value column="Name" original="Accounting Schema">Esquema contable</value><value column="Description" original="Maintain Accounting Schema - For changes to become effective you must re-login">Mantenimiento del esquema contable- Para que los cambios se actualicen debe volver a conectarse</value><value column="Help" original="The Accounting Schema Window defines an accounting method and the elements that will comprise an account structure. Create and activate elements for detailed accounting for Business Partners, Products, Locations, etc.Review and change the GL and Default accounts. The actual accounts used in transactions depend on the executing organization; Most of the information is derived from the context.">El esquema contable define el plan contable y las cuentas que lo componen. Crea y activa las cuentas para los productos, terceros, etc...Es necesario revisar y cambiar el libro mayor y las cuentas por defecto.El uso de las cuentas es propio de la organización.
&#13;</value></row><row id="128" trl="N"><value column="Name" original="GL Category">Categoría de LM</value><value column="Description" original="Maintain General Ledger Categories">Mantenimiento de las categorías del Libro Mayor</value><value column="Help" original="The GL Category Window allows you to define categories to be used in journals.  These categories provide a method of optionally grouping and reporting on journals.">La ventana de Categorías de Libro Mayor permite definir las categorías que se usaran en los diarios de asientos. Estas categorías proporcionan un metodo para agrupar y reportar opcionalmente en diarios de asientos.</value></row><row id="129" trl="N"><value column="Name" original="Document Type">Tipo de documento</value><value column="Description" original="Maintain Document Types">Mantenimiento de los tipos de documento</value><value column="Help" original="The Document Type Window defines any document to be used in the system.  Each document type provides the basis for processing of each document and controls the printed name and document sequence used.  ">La ventana de Tipo de documento define cualquier tipo de documento que se va a utilizar en el sistema. Cada tipo de documento define las reglas que hay que usar para procesarlo y controla el nombre impreso y la secuencia de documento usada.</value></row><row id="130" trl="N"><value column="Name" original="Document Sequence">Secuencia de documento (numeración)</value><value column="Description" original="Maintain System and Document Sequences">Mantenimiento de las secuencias del sistema y de los documentos</value><value column="Help" original="The Sequence Window defines how document numbers will be sequenced.Change the way document numbers are generated. You may add a prefix or a suffix or change the current number.">La ventana de secuencia de documento permite definir la secuencia (número de comienzo y razón de la serie) de numeración que seguirá cada uno de los documentos de la aplicación. Para cada documento, puede añadirse un prefijo o subfijo. Además puede configurarse cada secuencia de manera que se reinicie periódicamente.</value></row><row id="131" trl="N"><value column="Name" original="Business Partner Group">Grupos de Terceros</value><value column="Description" original="Maintain Business Partner Groups">Mantenimiento de los grupos de terceros</value><value column="Help" original="The Business Partner Group window allows you to define the accounting parameters at a group level.  If you define the accounting parameters for a group any Business Partner entered using this group will have these accounting parameters automatically populated.  You can then make any modifications necessary at the Business Partner level.">&lt;P&gt;Esta ventana permite definir unas condiciones de contabilidad a grupos de terceros. Si se asigna una condición de contabilidad a un grupo de terceros, cada uno de los terceros pertenecientes a este grupo tendrá asignado automáticamente las mismas condiciones de contabilidad.&lt;/P&gt;
&#13;&lt;P&gt;Existe la posibilidad de realizar modificaciones en dichas condiciones para cada tercero en particular.&lt;/P&gt;</value></row><row id="132" trl="N"><value column="Name" original="Greeting">Tratamientos</value><value column="Description" original="Maintain Greetings">Mantenimiento de tratamientos</value><value column="Help" original="The Greeting Window defines a greeting that is then associated with a Business Partner or Business Partner Contact.">&lt;P&gt;Mediante la ventana de Tratamientos se definen los tratamientos que puede recibir un socio de negocio o un contacto de un socio de negocio. &lt;/P&gt;
&#13;&lt;P&gt;Indistintamente del idioma se pueden introducir tantos tratamientos como se deseen. Además se puede introducir una descripción o traducción de cada tratamiento.&lt;/P&gt;</value></row><row id="133" trl="N"><value column="Name" original="Payment Term">Condiciones de pago</value><value column="Description" original="Maintain Payment Terms">Maintain Payment Terms</value><value column="Help" original="The Payment Terms Window defines the different payment terms that you offer your customers and that are offered to you by your vendors.  Each invoice must contain a Payment Term.  On the standard invoice, the Name and the Document Note of the Payment Term is printed.">&lt;P&gt;Mediante esta ventana se definen las diferentes condiciones de pago que ofrece a sus clientes y sus proveedores le ofrecen. Así como el programa de los pagos para cada tipo de condición de pago. Cada factura debe contener unas condiciones de pago.&lt;/P&gt;</value></row><row id="134" trl="N"><value column="Name" original="Invoice Schedule">Calendario de facturación</value><value column="Description" original="Maintain Invoicing Schedule">Mantenimiento del calendario de facturación</value><value column="Help" original="The Invoice Schedule Window defines the frequency and cut off dates for generating summary invoices.  If a customer requires a single invoice for multiple shipments you would define the appropriate invoice schedule and associate it with the Customer.">&lt;P&gt;La ventana de calendario de facturación define la frecuencia o periodicidad con la que se generan facturas totalizadas o agrupadas.&lt;/P&gt;
&#13;&lt;P&gt;Se utiliza cuando un cliente quiere en una sóla factura todos los guias de remisión  que se han creado durante el periodo definido. Para ello se asocia el cliente al calendario de facturación que requiera y que se haya definido previamente. &lt;/P&gt;</value></row><row id="135" trl="N"><value column="Name" original="Withholding (1099)">Retención (1099)</value><value column="Description" original="Maintain Withholding Certificates">Mantenimiento de documentos de retención</value><value column="Help" original="The Withholding Window defines the rule used for calculating withholding amounts.">La ventana de Mantenimiento de documentos de retención define las reglas que se utilizan para calcular las cantidades retenidas</value></row><row id="136" trl="N"><value column="Name" original="Dunning">Apremio</value><value column="Description" original="Maintain Dunning Levels">Mantenimiento de los niveles de apremio</value><value column="Help" original="The Dunning Window defines the parameters that will be used when generating Dunning Letters.  Each customer can be associated with a Dunning Code.  ">&lt;P&gt;La ventana de Apremio define los parametros que serán utilizados para generar las cartas de apremio. Cada cliente puede asociarse a un código de apremio.&lt;/P&gt;</value></row><row id="137" trl="N"><value column="Name" original="Revenue Recognition">Periodificación de ingresos</value><value column="Description" original="Revenue Recognition Rules">Reglas de periodificación de ingresos</value><value column="Help" original="The Revenue Recognition Window defines the intervals at which revenue will be recognized. Alternatively, the revenue recognition may be linked to service levels provided.">La ventana de Reglas de periodificación de ingresos define los intervalos que serán utilizados para reconocer ingresos. Alternativamente, los ingresos reconocidos podrán estar relacionados con los niveles de servicio provistos.</value></row><row id="138" trl="N"><value column="Name" original="Import Business Partner">Importar terceros</value><value column="Description" original="Import Business Partner">Importar terceros</value><value column="Help" original="The Import Business Partner Window is an interim table which is used when importing external data into the system.  Selecting the 'Process' button will either add or modify the appropriate records.">La ventana de Importar Terceros es una tabla intermedia que se utiliza cuando se importan datos externos al sistema. Si se selecciona el botón de "Proceso" se añadirán o modificaran los datos pertinentes.</value></row><row id="139" trl="N"><value column="Name" original="Business Partner">Terceros</value><value column="Description" original="Maintain Business Partners">Mantenimiento de terceros</value><value column="Help" original="The Business Partner window allows you do define any party with whom you transact.  This includes customers, vendors and employees.  Prior to entering or importing products, you must define your vendors.  Prior to generating Orders you must define your customers.  This window holds all information about your business partner and the values entered will be used to generate all document transactions">&lt;P&gt;La ventana de terceros permite definir los diferentes socios de negocio con los que establece relación de compra-venta la entidad.&lt;/P&gt;
&#13;&lt;P&gt;Existen tres tipos de terceros: Clientes, Proveedores y Empleados. Un mismo tercero puede mantener simultaneamente una relación de cliente y proveedor, cliente y empleado,...&lt;/P&gt;
&#13;&lt;P&gt;Antes de la entrada o la importación de productos, es necesario definir los proveedores. Igualemente, antes de la generación de pedidos de venta es necesario definir los clientes. Esta ventana contiene toda la información sobre su socio de negocio y los valores introducidos serán utilizados para generar todas las transacciones de documentos.&lt;/P&gt;</value></row><row id="140" trl="Y"><value column="Name" original="User">Usuario</value><value column="Description" original="Define Sales Representative as User">Definir los comerciales como usuarios de la aplicación.</value><value column="Help" original="Users can log into the system and have access to functionality via one or more roles. Select the Business Partner you just set up. This enables the user to be treated as sales rep in the system.">Los usuarios pueden hacer login en la aplicación y acceder a las diferentes funcionalidades en función de los roles asignados.</value></row><row id="141" trl="Y"><value column="Name" original="Business Partner">Tercero</value><value column="Description" original="Set up Sales Representative as Business Partner">Dar de alta los comerciales como terceros.</value><value column="Help" original="Set up the sales representative as Employee and Sales Representative in the Employee tab.  Also set up the Vendor part, if you want to create payments.">Dar de alta los comerciales como terceros. Así mismo, definirlo como cliente si queremos asignarle condiciones de pago.</value></row><row id="142" trl="N"><value column="Name" original="Sales Region">Zona de venta</value><value column="Description" original="Maintain Sales Regions">Mantenimiento de las zonas de venta</value><value column="Help" original="The Sales Region Window defines the different regions where you do business.  You can generate reports based on Sales Regions">&lt;P&gt;La ventana de Zona de Venta permite definir las regiones del área de negocio. Se pueden generar informes basados en estas zonas.&lt;/P&gt;</value></row><row id="143" trl="N"><value column="Name" original="Commission">Comisión</value><value column="Description" original="Maintain Commissions and Royalties">Mantenimento de comisiones</value><value column="Help" original="Define how and when you want the commissions to be calculated and to whom to pay it.The Commissions Window allows you define how commissions and royalties will be paid. You can pay multiple commissions for the same order or invoice (e.g. to the person entering the transaction, to the person responsible for sale of the product (category) and or business partner (group).">&lt;P&gt;Define como y cuando se desea calcular las comisiones y a quien pagarlas.&amp;nbsp;Es posible pagar varias comisiones en una misma factura.&lt;/P&gt;</value></row><row id="144" trl="N"><value column="Name" original="Marketing Channel">Canal de marketing</value><value column="Description" original="Maintain Marketing  Channels">Mantenimiento de los canales de marketing</value><value column="Help" original="The Marketing Channel Window defines the different channels used in Marketing Campaigns">La ventana de canal de marketing define los diferentes canales que se usan en las campañas de marketing.</value></row><row id="145" trl="N"><value column="Name" original="Marketing Campaign">Campaña de Marketing</value><value column="Description" original="Maintain Marketing Campaigns">Mantenimiento de las campañas de marketing</value><value column="Help" original="The Marketing Campaign Window defines the start and end date for a campaign.  It also gives a running balance of the invoice amounts which referred to this campaign.">En la ventana Campaña de Marketing se definen las diferentes campañas que se 
&#13;realizan en la empresa. </value></row><row id="146" trl="Y"><value column="Name" original="Workflow">Flujo de trabajo</value><value column="Description" original="Translate Workflows">Traducción de los flujos de trabajo</value><value column="Help" original="Translate Name, Description and Help of Workflows and their Nodes.  You only need to translate the List Elements !!">Traducción de los nombres, las descripciones y las ayudas de los flujos de trabajo y sus respectivos nodos. Solamente deben de traducirse los elementos de las listas.</value></row><row id="147" trl="N"><value column="Name" original="Performance Color">Color según rendimiento</value><value column="Description" original="Color used for Performance Analysis">Colores asociados según un rendimiento para el análisis</value><value column="Help" original="The Performance Color Window allows you to define the color schema to be used to indicate current performance.  The system has predefined Red (below 50%), Yellow (below 100%) and green above 100.  If you want to define your own color schema, do it here.">La ventana de Color según rendimiento permite definir el esquema de colores usado para indicar el performance actual. Por defecto el sistema utiliza el rojo (por debajo del 50%), amarillo (por debajo del 100%) y el verde por encima del 100%. Si quiere definir otro esquema de colores, hágalo aquí.</value></row><row id="148" trl="N"><value column="Name" original="Performance Measure Calculation">Cálculo de medidas de rendimiento</value><value column="Description" original="Define how you calculate your performance measures">Define como calcular las medidas de rendimiento</value><value column="Help" original="Please test the statement in SQL*Plus first.The select statement needs to return a single value!Any restrictions for Date range, Organizations, Business Partners, Products should be done via the &quot;Performance Measure&quot; window.  This is the generic calculation.As this tends to be somewhat technical, the system has a few examples predefined.">Please test the statement in SQL*Plus first.The select statement needs to return a single value!Any restrictions for Date range, Organizations, Business Partners, Products should be done via the "Performance Measure" window.  This is the generic calculation.As this tends to be somewhat technical, the system has a few examples predefined.</value></row><row id="149" trl="N"><value column="Name" original="Performance Measure">Medida de rendimiento</value><value column="Description" original="Define your Performance Measures">Define las medidas de rendimiento</value><value column="Help" original="The Performance Measure Window allows you to define the rules and restrictions for performance measurement.  You can, for example, restrict performance measurement to sales for a certain product category for a defined time frame.">La ventana de Medida de rendimiento permite definir las reglas y restricciones de la medida del performance. Se podrá, por ejemplo, restringir la medida del performance de ventas para una categoría de productos para un período de tiempo concreto.</value></row><row id="150" trl="N"><value column="Name" original="Performance Achievement">Resultado realización</value><value column="Description" original="Define Performance Achievements">Define los rendimientos de exito</value><value column="Help" original="The Performance Achievement Window allows you to define Tasks to be achieved.  The performance is measured by the percentage of reached achievements.">La ventana de resultado realización permite definir las tareas a ser realizadas. El resultado se mide según el porcentaje de avance/ logros en las tareas.</value></row><row id="151" trl="N"><value column="Name" original="Performance Color">Color según rendimiento</value><value column="Description" original="Color used for Performance Analysis">Colores asociados según un rendimiento para el análisis</value><value column="Help" original="The Performance Color Window allows you to define the color schema to be used to indicate current performance.  The system has predefined Red (below 50%), Yellow (below 100%) and green above 100.  If you want to define your own color schema, do it here.">La ventana de Color según rendimiento permite definir el esquema de colores usado para indicar el performance actual. Por defecto el sistema utiliza el rojo (por debajo del 50%), amarillo (por debajo del 100%) y el verde por encima del 100%. Si quiere definir otro esquema de colores, hágalo aquí.</value></row><row id="152" trl="N"><value column="Name" original="Check Client Setup">Check Client Setup</value><value column="Description" original="Check Client setup for Requests">Check Client setup for Requests</value><value column="Help" original="You need to have a mail server and an email address from which the requets an notifications are sent.  Optionally, if you define a mail user and password, requests are read from the mail users's folder and imported into the system.">You need to have a mail server and an email address from which the requets an notifications are sent.  Optionally, if you define a mail user and password, requests are read from the mail users's folder and imported into the system.</value></row><row id="153" trl="N"><value column="Name" original="Check Users">Check Users</value><value column="Description" original="Check users for Request processing">Check users for Request processing</value><value column="Help" original="Please ensure that users have a email address and supervisor assigned.">Please ensure that users have a email address and supervisor assigned.</value></row><row id="155" trl="Y"><value column="Name" original="Check Business Partners">Comprobar tercero</value><value column="Description" original="Check Business Partners for Request processing">Comprobar los procesos de peticiones de terceros.</value><value column="Help" original="You can send EMails to businbess partners.  Make sure, that the business partners and/or the Contacts have email addresses.">Se pueden enviar mails a los terceros. Asegurese de que el tercero y/o el tercero tienen configurado una dirección de correo electrónico.</value></row><row id="156" trl="N"><value column="Name" original="Request Processor">Procesador de peticiones</value><value column="Description" original="Define Request Processors">Definir los procesadores de peticiones</value><value column="Help" original="The Request Processor Window allows you to define different processes that you want to occur and the frequency and timing of these processes">La ventana de peticiones permite al usuario definir procesos, el tiempo y la frecuencia deseada para el seguimiento de cada petición.</value></row><row id="157" trl="N"><value column="Name" original="Request">CRM</value><value column="Description" original="Work on your requests">Trabajar sobre su petición</value><value column="Help" original="The Request Window is used to define and track any request assigned to you.">&lt;P&gt;Esta ventana permite gestionar las peticiones de los terceros con el fin de mejorar la relación. Cada petición puede desencadenar una acción o no, dependiendo de la naturaleza de la petición. Todas las peticiones deben de pertenecer a un tipo de petición.&lt;/P&gt;</value></row><row id="158" trl="N"><value column="Name" original="Warehouse &amp; Locator">bodega y huecos</value><value column="Description" original="Maintain Warehouses and Locators">Mantenimiento de bodegas y huecos</value><value column="Help" original="The Warehouse and Locators Window defines each Warehouse, any Locators for that Warehouse and the Accounting parameters to be used for inventory in that Warehouse.">En la ventana de bodega y huecos se definen los distintos bodegas que posee la empresa. Además, para cada bodega hay que indicar los huecos&amp;nbsp;en los que está constituido y el tipo de contabilidad que se va a llevar. </value></row><row id="159" trl="N"><value column="Name" original="Unit of Measure">Unidad de medida</value><value column="Description" original="Maintain Unit of Measure ">Mantenimiento de las unidades de medida</value><value column="Help" original="The Unit of Measure Window is used to define non monetary units of measure.  It also defines if conversion between units of measure are allowed and how they are to be performed. The system provides some automatic conversions between units of measures (e.g. minute, hour, day, working day, etc.) if they are not explicitly defined here.Conversions need to be direct (i.e. if you have only a conversion between A-B and B-C, the system cannot convert A-C, you need to define it explicitly).">La ventana Unidad de medida es usada para definir todas las unidades de medida no monetarias que se usan en el sistema. Tambiés se definen las conversiones entre medidas y sus factores de conversión.
&#13;
&#13;Las conversiones han de ser directas. Por ejemplo: si se tiene la conversión entre A-B y B-C el sistema no puede hacer la conversión entre A-C, ha de ser definida explícitamente.</value></row><row id="160" trl="N"><value column="Name" original="Product Category">Categoría del producto</value><value column="Description" original="Maintain Product Categories">Mantenimiento de las categorías del producto</value><value column="Help" original="The Product Category allows you to define different groups of products.  These groups can be used in generating Price Lists, defining margins and for easily assigning different accounting parameters for products.">La ventana Categoría del producto permite definir diferentes grupos de productos. Estos grupos se pueden usar para generar listas de precios, definir márgenes y para asignar fácilmente parámetros contables a los productos.</value></row><row id="161" trl="N"><value column="Name" original="Product">Producto</value><value column="Description" original="Maintain Products">Mantenimiento de los productos</value><value column="Help" original="The Product Window defines all products used by an organization.  These products include those sold to customers, used in the manufacture of products sold to customers and products purchased by an organization.">&lt;P&gt;La ventana de productos, permite definir todos los productos de una organización. Entre los productos se incluyen los fabricados por la propia organización y los comprados y vendidos por la organización a terceros.&lt;/P&gt;&#13;
&#13;
&lt;P&gt;Existen 4 tipos de productos diferentes, items, recursos, servicios y gastos. Cada uno de ellos recibe un tratamiento diferente. &lt;/P&gt;&#13;
&#13;
&lt;P&gt;Además, los items pueden ser listas de materiales y a cada producto se le puede definir un sustituto, un tipo de reposición, precio, proveedor,... &lt;/P&gt;</value></row><row id="162" trl="N"><value column="Name" original="Discount Schema">Esquema de tarificación</value><value column="Description" original="Maintain Trade Discount Schema">Mantenimiento del esquema de tarificación</value><value column="Help" original="Trade discount schema calculates the trade discount percentage">&lt;P&gt;La ventana de esquema de tarificación nos permite crear una lógica para la actualización de las tarifas creando nuevas versiones de tarificación.&lt;/P&gt;
&#13;&lt;P&gt;Un esquema de tarificación nos permite calcular nuevas versiones de tarifa realizando unas operaciones, previamente establecidas por nosotros en la solapa de Línea de tarifacación, sobre la lista de precios de una determinada tarifa. De este modo, evitamos tener que ir actualizando cada uno de los precios del catálogo manualmente.&lt;/P&gt;
&#13;&lt;P&gt;Un ejemplo claro puede ser la subida de precios a comienzos de año, donde muchos alimentos suben un porcentaje determinado su valor. Imaginemos un supermercado donde tendrían que actualizar todas sus listas de precios manualmente. Mediante el esquema de tarificación, podemos aumentar el precio de cada uno de los productos de una tarifa determinada un porcentaje equivalente al nivel de vida. Para ello sería suficiente con introducir una línea de tarificación con el porcentaje a incrementar.&lt;/P&gt;</value></row><row id="163" trl="N"><value column="Name" original="Price List">Tarifa</value><value column="Description" original="Maintain Product Price Lists">Mantenimiento de las tarifas de un producto</value><value column="Help" original="The Price List Window allows you to generate product price lists for your Business Partners.  Price lists determine currency and tax treatment.  Price list versions allow to maintain parallel lists for different date ranges.  The most current pricelist version is used based on the document date.&lt;BR&gt;All pricelists have three prices: List, Standard and Limit&lt;BR&gt;First step is to create a base price list.  You can manually add products and enter the prices or create them automatically.  The base price list is often the purchase price list with list price ('official' retail price), the standard price (your purchase price).  The limit price can be used to check your final purchase costs after discounts, rebates, etc.&lt;BR&gt; Pricelists can be calculated and copied.  To speed up the calculation, the parameters are stored an used when creating a new price list version.">&lt;P&gt;La ventana de tarifas permite generar listas de precios para los diferentes productos y terceros. Mediante las versiones de tarifa, es posible mantener los listados de precios de otros periodos. Se&amp;nbsp;&amp;nbsp;utiliza aquella versión que este en vigor.&lt;/P&gt;
&#13;&lt;P&gt;Todas las tarifas contienen tres precios por producto: precio tarifa, precio standar y precio límite.&lt;/P&gt;
&#13;&lt;P&gt;Primeramente se debe de crear una tarifa. Agregar productos a dicha tarifa, manual o automáticamente. La versión base contiene los precios sobre los que se va a calcular la nueva versión de tarifa. &lt;/P&gt;</value></row><row id="164" trl="N"><value column="Name" original="Business Partner">Terceros</value><value column="Description" original="Maintain Business Partners">Mantenimiento de terceros</value><value column="Help" original="The Business Partner window allows you do define any party with whom you transact.  This includes customers, vendors and employees.  Prior to entering or importing products, you must define your vendors.  Prior to generating Orders you must define your customers.  This window holds all information about your business partner and the values entered will be used to generate all document transactions">&lt;P&gt;La ventana de terceros permite definir los diferentes socios de negocio con los que establece relación de compra-venta la entidad.&lt;/P&gt;
&#13;&lt;P&gt;Existen tres tipos de terceros: Clientes, Proveedores y Empleados. Un mismo tercero puede mantener simultaneamente una relación de cliente y proveedor, cliente y empleado,...&lt;/P&gt;
&#13;&lt;P&gt;Antes de la entrada o la importación de productos, es necesario definir los proveedores. Igualemente, antes de la generación de pedidos de venta es necesario definir los clientes. Esta ventana contiene toda la información sobre su socio de negocio y los valores introducidos serán utilizados para generar todas las transacciones de documentos.&lt;/P&gt;</value></row><row id="166" trl="N"><value column="Name" original="Tax Category">Categoria de Impuesto</value><value column="Description" original="Maintain Tax Categories">Mantenimiento de las categorias de impuestos</value><value column="Help" original="The Tax Category Window is used to enter and maintain Tax Categories.  Each product is associated with a tax category which facilitates reacting changing tax rates.">La ventana de Categoría de Impuestos permite agrupar los diferentes rangos de impuestos por su categoría.</value></row><row id="167" trl="N"><value column="Name" original="Product">Producto</value><value column="Description" original="Maintain Products">Mantenimiento de los productos</value><value column="Help" original="The Product Window defines all products used by an organization.  These products include those sold to customers, used in the manufacture of products sold to customers and products purchased by an organization.">&lt;P&gt;La ventana de productos, permite definir todos los productos de una organización. Entre los productos se incluyen los fabricados por la propia organización y los comprados y vendidos por la organización a terceros.&lt;/P&gt;&#13;
&#13;
&lt;P&gt;Existen 4 tipos de productos diferentes, items, recursos, servicios y gastos. Cada uno de ellos recibe un tratamiento diferente. &lt;/P&gt;&#13;
&#13;
&lt;P&gt;Además, los items pueden ser listas de materiales y a cada producto se le puede definir un sustituto, un tipo de reposición, precio, proveedor,... &lt;/P&gt;</value></row><row id="168" trl="N"><value column="Name" original="Charge">Cobros</value><value column="Description" original="Maintain Charges">Mantenimiento de los cobros</value><value column="Help" original="The Charges Window defines the different charges that may be incurred.  These can include Bank Charges, Vendor Charges and Handling Charges.">La ventana de Mantenimiento de los cobros define los diferentes cargos que pueden. Estos cargos pueden ser cargos bancarios, cargos de un proveedor y cargos de manipulación</value></row><row id="169" trl="N"><value column="Name" original="Tax Rate">Rango impuesto</value><value column="Description" original="Maintain Taxes and their Rates">Mantenimiento de impuestos y sus rangos</value><value column="Help" original="The Tax Rate Window defines the different taxes used for each tax category.  For example, Sales Tax must be defined for each State in which it applies.">La ventana de Rangos de Impuestos permite configurar todo el árbol de impuestos de una organización. De esta manera, los diferentes rangos pertenecerán a una categoría. Y dentro de una árbol de impuestos se aplica uno y otro diferenciando si es compra o venta, por origen y destino, etc.</value></row><row id="170" trl="N"><value column="Name" original="Accounting Schema">Esquema contable</value><value column="Description" original="Maintain Accounting Schema - For changes to become effective you must re-login">Mantenimiento del esquema contable- Para que los cambios se actualicen debe volver a conectarse</value><value column="Help" original="The Accounting Schema Window defines an accounting method and the elements that will comprise an account structure. Create and activate elements for detailed accounting for Business Partners, Products, Locations, etc.Review and change the GL and Default accounts. The actual accounts used in transactions depend on the executing organization; Most of the information is derived from the context.">El esquema contable define el plan contable y las cuentas que lo componen. Crea y activa las cuentas para los productos, terceros, etc...Es necesario revisar y cambiar el libro mayor y las cuentas por defecto.El uso de las cuentas es propio de la organización.
&#13;</value></row><row id="171" trl="N"><value column="Name" original="Tax Category">Categoria de Impuesto</value><value column="Description" original="Maintain Tax Categories">Mantenimiento de las categorias de impuestos</value><value column="Help" original="The Tax Category Window is used to enter and maintain Tax Categories.  Each product is associated with a tax category which facilitates reacting changing tax rates.">La ventana de Categoría de Impuestos permite agrupar los diferentes rangos de impuestos por su categoría.</value></row><row id="172" trl="N"><value column="Name" original="Import File Loader">Importar fichero de carga</value><value column="Description" original="Load flat Files into import tables">Cargar ficheros planos a las tablas importadas</value><value column="Help" original="The Import File Loader parses the content of a flat file and loads it into import tables. Comments start with a '[' and end with a ']' and are ignored; example: [Some Heading].">Importar Fichero de Cargas parsea el contenido de un fichero de disco plano y lo carga en tablas de importación.Los comentarios empiezan con un '[' y terminan con un']' y son ignorados;ejemplo:[Algún Título]</value></row><row id="173" trl="N"><value column="Name" original="Import Account">Importar cuentas</value><value column="Description" original="Import Natural Account Values">Importar valores de cuentas</value><value column="Help" original="The Import Natural Account Window is an interim table which is used when importing external data into the system.  Selecting the 'Process' button will either add or modify the appropriate records.">La ventana de Importar valores de cuentas es una tabla intermedia que se utiliza cuando se importan datos externos al sistema. Si se selecciona el botón de "Proceso" se añadirán o modificaran los datos pertinentes.</value></row><row id="174" trl="N"><value column="Name" original="Replication Strategy">Estrategia de replicación</value><value column="Description" original="Maintain Data Replication Strategy">Mantenimiento de la estrategia de replicación</value><value column="Help" original="The Data Replication Strategy determines which tables and how they are replicated. Note that the migration does not syncronize Application Dictionary items.">La ventana de Estrategia de replicación determina que tablas y como son replicadas. Nota: La migración no sincroniza los items del Diccionario de Aplicación.</value></row><row id="175" trl="N"><value column="Name" original="Replication">Replicación</value><value column="Description" original="Maintain Data Replication Targets">Mantenimiento de los datos objetivo de la replicación</value><value column="Help" original="Data Replication Target Details. Set up your system completely on the central system, before setting up the replication. Define the Replication target here and export the database and import it on the remote system.&lt;p&gt;Before(!) entering transactions, Start the Replication Run to set up the remote system.">Datos de detalle de los objetivos de replicación. Configure su sistema completamente en el sistema central, antes de configurar la replicación. Defina el objetivo de la Replicación aquí y exporte e importe la base de datos en el sistema remoto. Antes de entrar transacciones, arranque la Replicación para configurar el sistema remoto.</value></row><row id="800000" trl="N"><value column="Name" original="Process">Proceso</value><value column="Description" original="Production processes setup.">Configuración de procesos productivos.</value><value column="Help" original="">En la pestaña proceso se describen los procesos que se hacen en el puesto de trabajo. </value></row><row id="800001" trl="N"><value column="Name" original="Cost Center">Centro de Costes</value><value column="Description" original="Cost Center configuration">Permite registrar los diferentes centros de costes que configuran el proceso de producción.</value><value column="Help" original="&lt;P&gt;In the cost center window there are all the cost center present on the enterprise.&lt;/P&gt;&#10;&#13;&lt;P&gt;&amp;nbsp;&lt;/P&gt;">&lt;P&gt;En la ventana de Centro de Costes (CC)&amp;nbsp;se recogen todos los&amp;nbsp;centros de coste&amp;nbsp;que hay en la empresa. &lt;/P&gt;
&#13;&lt;P&gt;Podríamos definir un centro de costes como&amp;nbsp;el instrumento contable que permite la acumulación de los costes de los factores productivos necesarios para realizar una determinada actividad o función. También conocido como grupo funcional homogeneo (GFH).&lt;/P&gt;
&#13;&lt;P&gt;Algunos de los factores productivos que se atribuyen a un centro de costes están relacionados con:&amp;nbsp;máquinas, instalaciones, hombres, mando,...&lt;/P&gt;</value></row><row id="800002" trl="N"><value column="Name" original="Cost Center UOM">Unidades de CC</value><value column="Description" original="Is the the Cost center Unit of measure window">Unidades del centro de costes</value><value column="Help" original="">Permite introducir las unidades  de medida del centro de costes.</value></row><row id="800003" trl="N"><value column="Name" original="Product">Producto</value><value column="Description" original="Maintain Products">Mantenimiento de los productos</value><value column="Help" original="The Product Window defines all products used by an organization.  These products include those sold to customers, used in the manufacture of products sold to customers and products purchased by an organization.">&lt;P&gt;La ventana de productos, permite definir todos los productos de una organización. Entre los productos se incluyen los fabricados por la propia organización y los comprados y vendidos por la organización a terceros.&lt;/P&gt;&#13;
&#13;
&lt;P&gt;Existen 4 tipos de productos diferentes, items, recursos, servicios y gastos. Cada uno de ellos recibe un tratamiento diferente. &lt;/P&gt;&#13;
&#13;
&lt;P&gt;Además, los items pueden ser listas de materiales y a cada producto se le puede definir un sustituto, un tipo de reposición, precio, proveedor,... &lt;/P&gt;</value></row></compiereTrl>