<?xml version='1.0' encoding='UTF-8'?>
<data>
<!--
************************
0. Core Range.
************************
-->
<!--
************************
0. End of Core Range.
************************
-->
<!--
************************
1. Custom Range.
************************
-->
<!--1000000 1000000**************--><C_TAX_ACCT>
<!--1000000 1000000 C_TAX_ID-->
<!--1000000 1000000-->              <C_TAX_ID><![CDATA[1000000]]></C_TAX_ID>
<!--1000000 1000000 C_ACCTSCHEMA_ID-->
<!--1000000 1000000-->              <C_ACCTSCHEMA_ID><![CDATA[1000000]]></C_ACCTSCHEMA_ID>
<!--1000000 1000000 AD_CLIENT_ID-->
<!--1000000 1000000-->              <AD_CLIENT_ID><![CDATA[1000000]]></AD_CLIENT_ID>
<!--1000000 1000000 AD_ORG_ID-->
<!--1000000 1000000-->              <AD_ORG_ID><![CDATA[0]]></AD_ORG_ID>
<!--1000000 1000000 ISACTIVE-->
<!--1000000 1000000-->              <ISACTIVE><![CDATA[Y]]></ISACTIVE>
<!--1000000 1000000 CREATED-->
<!--1000000 1000000-->              <CREATED><![CDATA[2006-03-14 20:51:17.0]]></CREATED>
<!--1000000 1000000 CREATEDBY-->
<!--1000000 1000000-->              <CREATEDBY><![CDATA[0]]></CREATEDBY>
<!--1000000 1000000 UPDATED-->
<!--1000000 1000000-->              <UPDATED><![CDATA[2006-03-14 20:51:17.0]]></UPDATED>
<!--1000000 1000000 UPDATEDBY-->
<!--1000000 1000000-->              <UPDATEDBY><![CDATA[0]]></UPDATEDBY>
<!--1000000 1000000 T_DUE_ACCT-->
<!--1000000 1000000-->              <T_DUE_ACCT><![CDATA[1000040]]></T_DUE_ACCT>
<!--1000000 1000000 T_LIABILITY_ACCT-->
<!--1000000 1000000-->              <T_LIABILITY_ACCT><![CDATA[1000038]]></T_LIABILITY_ACCT>
<!--1000000 1000000 T_CREDIT_ACCT-->
<!--1000000 1000000-->              <T_CREDIT_ACCT><![CDATA[1000041]]></T_CREDIT_ACCT>
<!--1000000 1000000 T_RECEIVABLES_ACCT-->
<!--1000000 1000000-->              <T_RECEIVABLES_ACCT><![CDATA[1000039]]></T_RECEIVABLES_ACCT>
<!--1000000 1000000 T_EXPENSE_ACCT-->
<!--1000000 1000000-->              <T_EXPENSE_ACCT><![CDATA[1000037]]></T_EXPENSE_ACCT>
<!--1000000 1000000**************--></C_TAX_ACCT>

<!--1000001 1000000**************--><C_TAX_ACCT>
<!--1000001 1000000 C_TAX_ID-->
<!--1000001 1000000-->              <C_TAX_ID><![CDATA[1000001]]></C_TAX_ID>
<!--1000001 1000000 C_ACCTSCHEMA_ID-->
<!--1000001 1000000-->              <C_ACCTSCHEMA_ID><![CDATA[1000000]]></C_ACCTSCHEMA_ID>
<!--1000001 1000000 AD_CLIENT_ID-->
<!--1000001 1000000-->              <AD_CLIENT_ID><![CDATA[1000000]]></AD_CLIENT_ID>
<!--1000001 1000000 AD_ORG_ID-->
<!--1000001 1000000-->              <AD_ORG_ID><![CDATA[0]]></AD_ORG_ID>
<!--1000001 1000000 ISACTIVE-->
<!--1000001 1000000-->              <ISACTIVE><![CDATA[Y]]></ISACTIVE>
<!--1000001 1000000 CREATED-->
<!--1000001 1000000-->              <CREATED><![CDATA[2006-03-15 11:12:40.0]]></CREATED>
<!--1000001 1000000 CREATEDBY-->
<!--1000001 1000000-->              <CREATEDBY><![CDATA[1000000]]></CREATEDBY>
<!--1000001 1000000 UPDATED-->
<!--1000001 1000000-->              <UPDATED><![CDATA[2006-03-15 11:12:40.0]]></UPDATED>
<!--1000001 1000000 UPDATEDBY-->
<!--1000001 1000000-->              <UPDATEDBY><![CDATA[1000000]]></UPDATEDBY>
<!--1000001 1000000 T_DUE_ACCT-->
<!--1000001 1000000-->              <T_DUE_ACCT><![CDATA[1000040]]></T_DUE_ACCT>
<!--1000001 1000000 T_LIABILITY_ACCT-->
<!--1000001 1000000-->              <T_LIABILITY_ACCT><![CDATA[1000038]]></T_LIABILITY_ACCT>
<!--1000001 1000000 T_CREDIT_ACCT-->
<!--1000001 1000000-->              <T_CREDIT_ACCT><![CDATA[1000041]]></T_CREDIT_ACCT>
<!--1000001 1000000 T_RECEIVABLES_ACCT-->
<!--1000001 1000000-->              <T_RECEIVABLES_ACCT><![CDATA[1000039]]></T_RECEIVABLES_ACCT>
<!--1000001 1000000 T_EXPENSE_ACCT-->
<!--1000001 1000000-->              <T_EXPENSE_ACCT><![CDATA[1000037]]></T_EXPENSE_ACCT>
<!--1000001 1000000**************--></C_TAX_ACCT>

<!--1000002 1000000**************--><C_TAX_ACCT>
<!--1000002 1000000 C_TAX_ID-->
<!--1000002 1000000-->              <C_TAX_ID><![CDATA[1000002]]></C_TAX_ID>
<!--1000002 1000000 C_ACCTSCHEMA_ID-->
<!--1000002 1000000-->              <C_ACCTSCHEMA_ID><![CDATA[1000000]]></C_ACCTSCHEMA_ID>
<!--1000002 1000000 AD_CLIENT_ID-->
<!--1000002 1000000-->              <AD_CLIENT_ID><![CDATA[1000000]]></AD_CLIENT_ID>
<!--1000002 1000000 AD_ORG_ID-->
<!--1000002 1000000-->              <AD_ORG_ID><![CDATA[0]]></AD_ORG_ID>
<!--1000002 1000000 ISACTIVE-->
<!--1000002 1000000-->              <ISACTIVE><![CDATA[Y]]></ISACTIVE>
<!--1000002 1000000 CREATED-->
<!--1000002 1000000-->              <CREATED><![CDATA[2006-03-15 11:13:45.0]]></CREATED>
<!--1000002 1000000 CREATEDBY-->
<!--1000002 1000000-->              <CREATEDBY><![CDATA[1000000]]></CREATEDBY>
<!--1000002 1000000 UPDATED-->
<!--1000002 1000000-->              <UPDATED><![CDATA[2006-03-15 11:13:45.0]]></UPDATED>
<!--1000002 1000000 UPDATEDBY-->
<!--1000002 1000000-->              <UPDATEDBY><![CDATA[1000000]]></UPDATEDBY>
<!--1000002 1000000 T_DUE_ACCT-->
<!--1000002 1000000-->              <T_DUE_ACCT><![CDATA[1000040]]></T_DUE_ACCT>
<!--1000002 1000000 T_LIABILITY_ACCT-->
<!--1000002 1000000-->              <T_LIABILITY_ACCT><![CDATA[1000038]]></T_LIABILITY_ACCT>
<!--1000002 1000000 T_CREDIT_ACCT-->
<!--1000002 1000000-->              <T_CREDIT_ACCT><![CDATA[1000041]]></T_CREDIT_ACCT>
<!--1000002 1000000 T_RECEIVABLES_ACCT-->
<!--1000002 1000000-->              <T_RECEIVABLES_ACCT><![CDATA[1000039]]></T_RECEIVABLES_ACCT>
<!--1000002 1000000 T_EXPENSE_ACCT-->
<!--1000002 1000000-->              <T_EXPENSE_ACCT><![CDATA[1000037]]></T_EXPENSE_ACCT>
<!--1000002 1000000**************--></C_TAX_ACCT>

<!--1000003 1000000**************--><C_TAX_ACCT>
<!--1000003 1000000 C_TAX_ID-->
<!--1000003 1000000-->              <C_TAX_ID><![CDATA[1000003]]></C_TAX_ID>
<!--1000003 1000000 C_ACCTSCHEMA_ID-->
<!--1000003 1000000-->              <C_ACCTSCHEMA_ID><![CDATA[1000000]]></C_ACCTSCHEMA_ID>
<!--1000003 1000000 AD_CLIENT_ID-->
<!--1000003 1000000-->              <AD_CLIENT_ID><![CDATA[1000000]]></AD_CLIENT_ID>
<!--1000003 1000000 AD_ORG_ID-->
<!--1000003 1000000-->              <AD_ORG_ID><![CDATA[0]]></AD_ORG_ID>
<!--1000003 1000000 ISACTIVE-->
<!--1000003 1000000-->              <ISACTIVE><![CDATA[Y]]></ISACTIVE>
<!--1000003 1000000 CREATED-->
<!--1000003 1000000-->              <CREATED><![CDATA[2006-03-15 11:16:21.0]]></CREATED>
<!--1000003 1000000 CREATEDBY-->
<!--1000003 1000000-->              <CREATEDBY><![CDATA[1000000]]></CREATEDBY>
<!--1000003 1000000 UPDATED-->
<!--1000003 1000000-->              <UPDATED><![CDATA[2006-03-15 11:16:21.0]]></UPDATED>
<!--1000003 1000000 UPDATEDBY-->
<!--1000003 1000000-->              <UPDATEDBY><![CDATA[1000000]]></UPDATEDBY>
<!--1000003 1000000 T_DUE_ACCT-->
<!--1000003 1000000-->              <T_DUE_ACCT><![CDATA[1000040]]></T_DUE_ACCT>
<!--1000003 1000000 T_LIABILITY_ACCT-->
<!--1000003 1000000-->              <T_LIABILITY_ACCT><![CDATA[1000038]]></T_LIABILITY_ACCT>
<!--1000003 1000000 T_CREDIT_ACCT-->
<!--1000003 1000000-->              <T_CREDIT_ACCT><![CDATA[1000041]]></T_CREDIT_ACCT>
<!--1000003 1000000 T_RECEIVABLES_ACCT-->
<!--1000003 1000000-->              <T_RECEIVABLES_ACCT><![CDATA[1000039]]></T_RECEIVABLES_ACCT>
<!--1000003 1000000 T_EXPENSE_ACCT-->
<!--1000003 1000000-->              <T_EXPENSE_ACCT><![CDATA[1000037]]></T_EXPENSE_ACCT>
<!--1000003 1000000**************--></C_TAX_ACCT>

<!--1000004 1000000**************--><C_TAX_ACCT>
<!--1000004 1000000 C_TAX_ID-->
<!--1000004 1000000-->              <C_TAX_ID><![CDATA[1000004]]></C_TAX_ID>
<!--1000004 1000000 C_ACCTSCHEMA_ID-->
<!--1000004 1000000-->              <C_ACCTSCHEMA_ID><![CDATA[1000000]]></C_ACCTSCHEMA_ID>
<!--1000004 1000000 AD_CLIENT_ID-->
<!--1000004 1000000-->              <AD_CLIENT_ID><![CDATA[1000000]]></AD_CLIENT_ID>
<!--1000004 1000000 AD_ORG_ID-->
<!--1000004 1000000-->              <AD_ORG_ID><![CDATA[0]]></AD_ORG_ID>
<!--1000004 1000000 ISACTIVE-->
<!--1000004 1000000-->              <ISACTIVE><![CDATA[Y]]></ISACTIVE>
<!--1000004 1000000 CREATED-->
<!--1000004 1000000-->              <CREATED><![CDATA[2006-03-15 13:33:03.0]]></CREATED>
<!--1000004 1000000 CREATEDBY-->
<!--1000004 1000000-->              <CREATEDBY><![CDATA[1000000]]></CREATEDBY>
<!--1000004 1000000 UPDATED-->
<!--1000004 1000000-->              <UPDATED><![CDATA[2006-03-15 13:33:03.0]]></UPDATED>
<!--1000004 1000000 UPDATEDBY-->
<!--1000004 1000000-->              <UPDATEDBY><![CDATA[1000000]]></UPDATEDBY>
<!--1000004 1000000 T_DUE_ACCT-->
<!--1000004 1000000-->              <T_DUE_ACCT><![CDATA[1000040]]></T_DUE_ACCT>
<!--1000004 1000000 T_LIABILITY_ACCT-->
<!--1000004 1000000-->              <T_LIABILITY_ACCT><![CDATA[1000038]]></T_LIABILITY_ACCT>
<!--1000004 1000000 T_CREDIT_ACCT-->
<!--1000004 1000000-->              <T_CREDIT_ACCT><![CDATA[1000041]]></T_CREDIT_ACCT>
<!--1000004 1000000 T_RECEIVABLES_ACCT-->
<!--1000004 1000000-->              <T_RECEIVABLES_ACCT><![CDATA[1000039]]></T_RECEIVABLES_ACCT>
<!--1000004 1000000 T_EXPENSE_ACCT-->
<!--1000004 1000000-->              <T_EXPENSE_ACCT><![CDATA[1000037]]></T_EXPENSE_ACCT>
<!--1000004 1000000**************--></C_TAX_ACCT>

<!--1000005 1000000**************--><C_TAX_ACCT>
<!--1000005 1000000 C_TAX_ID-->
<!--1000005 1000000-->              <C_TAX_ID><![CDATA[1000005]]></C_TAX_ID>
<!--1000005 1000000 C_ACCTSCHEMA_ID-->
<!--1000005 1000000-->              <C_ACCTSCHEMA_ID><![CDATA[1000000]]></C_ACCTSCHEMA_ID>
<!--1000005 1000000 AD_CLIENT_ID-->
<!--1000005 1000000-->              <AD_CLIENT_ID><![CDATA[1000000]]></AD_CLIENT_ID>
<!--1000005 1000000 AD_ORG_ID-->
<!--1000005 1000000-->              <AD_ORG_ID><![CDATA[0]]></AD_ORG_ID>
<!--1000005 1000000 ISACTIVE-->
<!--1000005 1000000-->              <ISACTIVE><![CDATA[Y]]></ISACTIVE>
<!--1000005 1000000 CREATED-->
<!--1000005 1000000-->              <CREATED><![CDATA[2006-03-15 13:37:43.0]]></CREATED>
<!--1000005 1000000 CREATEDBY-->
<!--1000005 1000000-->              <CREATEDBY><![CDATA[1000000]]></CREATEDBY>
<!--1000005 1000000 UPDATED-->
<!--1000005 1000000-->              <UPDATED><![CDATA[2006-03-15 13:37:43.0]]></UPDATED>
<!--1000005 1000000 UPDATEDBY-->
<!--1000005 1000000-->              <UPDATEDBY><![CDATA[1000000]]></UPDATEDBY>
<!--1000005 1000000 T_DUE_ACCT-->
<!--1000005 1000000-->              <T_DUE_ACCT><![CDATA[1000040]]></T_DUE_ACCT>
<!--1000005 1000000 T_LIABILITY_ACCT-->
<!--1000005 1000000-->              <T_LIABILITY_ACCT><![CDATA[1000038]]></T_LIABILITY_ACCT>
<!--1000005 1000000 T_CREDIT_ACCT-->
<!--1000005 1000000-->              <T_CREDIT_ACCT><![CDATA[1000041]]></T_CREDIT_ACCT>
<!--1000005 1000000 T_RECEIVABLES_ACCT-->
<!--1000005 1000000-->              <T_RECEIVABLES_ACCT><![CDATA[1000039]]></T_RECEIVABLES_ACCT>
<!--1000005 1000000 T_EXPENSE_ACCT-->
<!--1000005 1000000-->              <T_EXPENSE_ACCT><![CDATA[1000037]]></T_EXPENSE_ACCT>
<!--1000005 1000000**************--></C_TAX_ACCT>

<!--1000006 1000000**************--><C_TAX_ACCT>
<!--1000006 1000000 C_TAX_ID-->
<!--1000006 1000000-->              <C_TAX_ID><![CDATA[1000006]]></C_TAX_ID>
<!--1000006 1000000 C_ACCTSCHEMA_ID-->
<!--1000006 1000000-->              <C_ACCTSCHEMA_ID><![CDATA[1000000]]></C_ACCTSCHEMA_ID>
<!--1000006 1000000 AD_CLIENT_ID-->
<!--1000006 1000000-->              <AD_CLIENT_ID><![CDATA[1000000]]></AD_CLIENT_ID>
<!--1000006 1000000 AD_ORG_ID-->
<!--1000006 1000000-->              <AD_ORG_ID><![CDATA[0]]></AD_ORG_ID>
<!--1000006 1000000 ISACTIVE-->
<!--1000006 1000000-->              <ISACTIVE><![CDATA[Y]]></ISACTIVE>
<!--1000006 1000000 CREATED-->
<!--1000006 1000000-->              <CREATED><![CDATA[2006-03-15 13:39:17.0]]></CREATED>
<!--1000006 1000000 CREATEDBY-->
<!--1000006 1000000-->              <CREATEDBY><![CDATA[1000000]]></CREATEDBY>
<!--1000006 1000000 UPDATED-->
<!--1000006 1000000-->              <UPDATED><![CDATA[2006-03-15 13:39:17.0]]></UPDATED>
<!--1000006 1000000 UPDATEDBY-->
<!--1000006 1000000-->              <UPDATEDBY><![CDATA[1000000]]></UPDATEDBY>
<!--1000006 1000000 T_DUE_ACCT-->
<!--1000006 1000000-->              <T_DUE_ACCT><![CDATA[1000040]]></T_DUE_ACCT>
<!--1000006 1000000 T_LIABILITY_ACCT-->
<!--1000006 1000000-->              <T_LIABILITY_ACCT><![CDATA[1000038]]></T_LIABILITY_ACCT>
<!--1000006 1000000 T_CREDIT_ACCT-->
<!--1000006 1000000-->              <T_CREDIT_ACCT><![CDATA[1000041]]></T_CREDIT_ACCT>
<!--1000006 1000000 T_RECEIVABLES_ACCT-->
<!--1000006 1000000-->              <T_RECEIVABLES_ACCT><![CDATA[1000039]]></T_RECEIVABLES_ACCT>
<!--1000006 1000000 T_EXPENSE_ACCT-->
<!--1000006 1000000-->              <T_EXPENSE_ACCT><![CDATA[1000037]]></T_EXPENSE_ACCT>
<!--1000006 1000000**************--></C_TAX_ACCT>

<!--1000007 1000001**************--><C_TAX_ACCT>
<!--1000007 1000001 C_TAX_ID-->
<!--1000007 1000001-->              <C_TAX_ID><![CDATA[1000007]]></C_TAX_ID>
<!--1000007 1000001 C_ACCTSCHEMA_ID-->
<!--1000007 1000001-->              <C_ACCTSCHEMA_ID><![CDATA[1000001]]></C_ACCTSCHEMA_ID>
<!--1000007 1000001 AD_CLIENT_ID-->
<!--1000007 1000001-->              <AD_CLIENT_ID><![CDATA[1000001]]></AD_CLIENT_ID>
<!--1000007 1000001 AD_ORG_ID-->
<!--1000007 1000001-->              <AD_ORG_ID><![CDATA[0]]></AD_ORG_ID>
<!--1000007 1000001 ISACTIVE-->
<!--1000007 1000001-->              <ISACTIVE><![CDATA[Y]]></ISACTIVE>
<!--1000007 1000001 CREATED-->
<!--1000007 1000001-->              <CREATED><![CDATA[2007-12-11 11:59:25.0]]></CREATED>
<!--1000007 1000001 CREATEDBY-->
<!--1000007 1000001-->              <CREATEDBY><![CDATA[0]]></CREATEDBY>
<!--1000007 1000001 UPDATED-->
<!--1000007 1000001-->              <UPDATED><![CDATA[2007-12-18 11:30:27.0]]></UPDATED>
<!--1000007 1000001 UPDATEDBY-->
<!--1000007 1000001-->              <UPDATEDBY><![CDATA[0]]></UPDATEDBY>
<!--1000007 1000001 T_DUE_ACCT-->
<!--1000007 1000001-->              <T_DUE_ACCT><![CDATA[1000089]]></T_DUE_ACCT>
<!--1000007 1000001 T_CREDIT_ACCT-->
<!--1000007 1000001-->              <T_CREDIT_ACCT><![CDATA[1000090]]></T_CREDIT_ACCT>
<!--1000007 1000001**************--></C_TAX_ACCT>

<!--1000008 1000001**************--><C_TAX_ACCT>
<!--1000008 1000001 C_TAX_ID-->
<!--1000008 1000001-->              <C_TAX_ID><![CDATA[1000008]]></C_TAX_ID>
<!--1000008 1000001 C_ACCTSCHEMA_ID-->
<!--1000008 1000001-->              <C_ACCTSCHEMA_ID><![CDATA[1000001]]></C_ACCTSCHEMA_ID>
<!--1000008 1000001 AD_CLIENT_ID-->
<!--1000008 1000001-->              <AD_CLIENT_ID><![CDATA[1000001]]></AD_CLIENT_ID>
<!--1000008 1000001 AD_ORG_ID-->
<!--1000008 1000001-->              <AD_ORG_ID><![CDATA[0]]></AD_ORG_ID>
<!--1000008 1000001 ISACTIVE-->
<!--1000008 1000001-->              <ISACTIVE><![CDATA[Y]]></ISACTIVE>
<!--1000008 1000001 CREATED-->
<!--1000008 1000001-->              <CREATED><![CDATA[2007-12-11 12:13:46.0]]></CREATED>
<!--1000008 1000001 CREATEDBY-->
<!--1000008 1000001-->              <CREATEDBY><![CDATA[100]]></CREATEDBY>
<!--1000008 1000001 UPDATED-->
<!--1000008 1000001-->              <UPDATED><![CDATA[2007-12-18 11:30:27.0]]></UPDATED>
<!--1000008 1000001 UPDATEDBY-->
<!--1000008 1000001-->              <UPDATEDBY><![CDATA[0]]></UPDATEDBY>
<!--1000008 1000001 T_DUE_ACCT-->
<!--1000008 1000001-->              <T_DUE_ACCT><![CDATA[1000089]]></T_DUE_ACCT>
<!--1000008 1000001 T_CREDIT_ACCT-->
<!--1000008 1000001-->              <T_CREDIT_ACCT><![CDATA[1000090]]></T_CREDIT_ACCT>
<!--1000008 1000001**************--></C_TAX_ACCT>

<!--
************************
1. End of Custom Range.
************************
-->
</data>
