<?xml version="1.0"?>
  <database name="TABLE C_DOCTYPE_TRL">
    <table name="C_DOCTYPE_TRL" primaryKey="C_DOCTYPE_TRL_KEY">
      <column name="C_DOCTYPE_ID" primaryKey="true" required="true" type="DECIMAL" size="10,0" autoIncrement="false"/>
      <column name="AD_LANGUAGE" primaryKey="true" required="true" type="VARCHAR" size="6" autoIncrement="false"/>
      <column name="AD_CLIENT_ID" primaryKey="false" required="true" type="DECIMAL" size="10,0" autoIncrement="false"/>
      <column name="AD_ORG_ID" primaryKey="false" required="true" type="DECIMAL" size="10,0" autoIncrement="false"/>
      <column name="ISACTIVE" primaryKey="false" required="true" type="CHAR" size="1" default="Y" autoIncrement="false"/>
      <column name="CREATED" primaryKey="false" required="true" type="TIMESTAMP" size="7" default="SYSDATE" autoIncrement="false"/>
      <column name="CREATEDBY" primaryKey="false" required="true" type="DECIMAL" size="10,0" autoIncrement="false"/>
      <column name="UPDATED" primaryKey="false" required="true" type="TIMESTAMP" size="7" default="SYSDATE" autoIncrement="false"/>
      <column name="UPDATEDBY" primaryKey="false" required="true" type="DECIMAL" size="10,0" autoIncrement="false"/>
      <column name="NAME" primaryKey="false" required="true" type="NVARCHAR" size="60" autoIncrement="false"/>
      <column name="PRINTNAME" primaryKey="false" required="true" type="NVARCHAR" size="60" autoIncrement="false"/>
      <column name="DOCUMENTNOTE" primaryKey="false" required="false" type="NVARCHAR" size="2000" autoIncrement="false"/>
      <column name="ISTRANSLATED" primaryKey="false" required="true" type="CHAR" size="1" default="N" autoIncrement="false"/>
      <foreign-key foreignTable="AD_CLIENT" name="ADCLIENT_CDOCTYPETRL">
        <reference local="AD_CLIENT_ID" foreign="AD_CLIENT_ID"/>
      </foreign-key>
      <foreign-key foreignTable="AD_LANGUAGE" name="ADLANGUAGE_CDOCTYPETRL">
        <reference local="AD_LANGUAGE" foreign="AD_LANGUAGE"/>
      </foreign-key>
      <foreign-key foreignTable="AD_ORG" name="ADORG_CDOCTYPETRL">
        <reference local="AD_ORG_ID" foreign="AD_ORG_ID"/>
      </foreign-key>
      <foreign-key foreignTable="C_DOCTYPE" name="CDOCTYPE_CDOCTYPETRL" onDelete="cascade">
        <reference local="C_DOCTYPE_ID" foreign="C_DOCTYPE_ID"/>
      </foreign-key>
      <check name="CDOCTYPETRL_ISTRANSLAT_CHECK"><![CDATA[ISTRANSLATED IN ('Y', 'N')]]></check>
      <check name="C_DOCTYPE_TRL_ISACTIVE_CHECK"><![CDATA[ISACTIVE IN ('Y', 'N')]]></check>
    </table>
  </database>
