<?xml version='1.0' encoding='UTF-8'?>
<data>
<!--
************************
0. Core Range.
************************
-->
<!--AD_PREFERENCE_ID=1000100001-->                    <AD_PREFERENCE>
<!--AD_PREFERENCE_ID=1000100001 AD_PREFERENCE_ID-->
<!--AD_PREFERENCE_ID=1000100001-->                        <AD_PREFERENCE_ID><![CDATA[1000100001]]></AD_PREFERENCE_ID>
<!--AD_PREFERENCE_ID=1000100001 AD_CLIENT_ID-->
<!--AD_PREFERENCE_ID=1000100001-->                        <AD_CLIENT_ID><![CDATA[1000000]]></AD_CLIENT_ID>
<!--AD_PREFERENCE_ID=1000100001 AD_ORG_ID-->
<!--AD_PREFERENCE_ID=1000100001-->                        <AD_ORG_ID><![CDATA[1000000]]></AD_ORG_ID>
<!--AD_PREFERENCE_ID=1000100001 ISACTIVE-->
<!--AD_PREFERENCE_ID=1000100001-->                        <ISACTIVE><![CDATA[Y]]></ISACTIVE>
<!--AD_PREFERENCE_ID=1000100001 CREATED-->
<!--AD_PREFERENCE_ID=1000100001-->                        <CREATED><![CDATA[2008-01-18 14:52:15.0]]></CREATED>
<!--AD_PREFERENCE_ID=1000100001 CREATEDBY-->
<!--AD_PREFERENCE_ID=1000100001-->                        <CREATEDBY><![CDATA[100]]></CREATEDBY>
<!--AD_PREFERENCE_ID=1000100001 UPDATED-->
<!--AD_PREFERENCE_ID=1000100001-->                        <UPDATED><![CDATA[2008-01-18 15:24:14.0]]></UPDATED>
<!--AD_PREFERENCE_ID=1000100001 UPDATEDBY-->
<!--AD_PREFERENCE_ID=1000100001-->                        <UPDATEDBY><![CDATA[100]]></UPDATEDBY>
<!--AD_PREFERENCE_ID=1000100001 AD_WINDOW_ID-->
<!--AD_PREFERENCE_ID=1000100001-->                        <AD_WINDOW_ID><![CDATA[800004]]></AD_WINDOW_ID>
<!--AD_PREFERENCE_ID=1000100001 ATTRIBUTE-->
<!--AD_PREFERENCE_ID=1000100001-->                        <ATTRIBUTE><![CDATA[C_DocTypeTarget_ID]]></ATTRIBUTE>
<!--AD_PREFERENCE_ID=1000100001 VALUE-->
<!--AD_PREFERENCE_ID=1000100001-->                        <VALUE><![CDATA[1000026]]></VALUE>
<!--AD_PREFERENCE_ID=1000100001-->                    </AD_PREFERENCE>
<!--
************************
0. End of Core Range.
************************
-->
<!--
************************
1. Custom Range.
************************
-->
<!--AD_PREFERENCE_ID=1000000-->                    <AD_PREFERENCE>
<!--AD_PREFERENCE_ID=1000000 AD_PREFERENCE_ID-->
<!--AD_PREFERENCE_ID=1000000-->                        <AD_PREFERENCE_ID><![CDATA[1000000]]></AD_PREFERENCE_ID>
<!--AD_PREFERENCE_ID=1000000 AD_CLIENT_ID-->
<!--AD_PREFERENCE_ID=1000000-->                        <AD_CLIENT_ID><![CDATA[1000000]]></AD_CLIENT_ID>
<!--AD_PREFERENCE_ID=1000000 AD_ORG_ID-->
<!--AD_PREFERENCE_ID=1000000-->                        <AD_ORG_ID><![CDATA[0]]></AD_ORG_ID>
<!--AD_PREFERENCE_ID=1000000 ISACTIVE-->
<!--AD_PREFERENCE_ID=1000000-->                        <ISACTIVE><![CDATA[Y]]></ISACTIVE>
<!--AD_PREFERENCE_ID=1000000 CREATED-->
<!--AD_PREFERENCE_ID=1000000-->                        <CREATED><![CDATA[2006-03-14 20:51:16.0]]></CREATED>
<!--AD_PREFERENCE_ID=1000000 CREATEDBY-->
<!--AD_PREFERENCE_ID=1000000-->                        <CREATEDBY><![CDATA[0]]></CREATEDBY>
<!--AD_PREFERENCE_ID=1000000 UPDATED-->
<!--AD_PREFERENCE_ID=1000000-->                        <UPDATED><![CDATA[2006-04-01 20:45:28.0]]></UPDATED>
<!--AD_PREFERENCE_ID=1000000 UPDATEDBY-->
<!--AD_PREFERENCE_ID=1000000-->                        <UPDATEDBY><![CDATA[100]]></UPDATEDBY>
<!--AD_PREFERENCE_ID=1000000 AD_WINDOW_ID-->
<!--AD_PREFERENCE_ID=1000000-->                        <AD_WINDOW_ID><![CDATA[143]]></AD_WINDOW_ID>
<!--AD_PREFERENCE_ID=1000000 ATTRIBUTE-->
<!--AD_PREFERENCE_ID=1000000-->                        <ATTRIBUTE><![CDATA[C_DocTypeTarget_ID]]></ATTRIBUTE>
<!--AD_PREFERENCE_ID=1000000 VALUE-->
<!--AD_PREFERENCE_ID=1000000-->                        <VALUE><![CDATA[1000026]]></VALUE>
<!--AD_PREFERENCE_ID=1000000-->                    </AD_PREFERENCE>
<!--AD_PREFERENCE_ID=1000001-->                    <AD_PREFERENCE>
<!--AD_PREFERENCE_ID=1000001 AD_PREFERENCE_ID-->
<!--AD_PREFERENCE_ID=1000001-->                        <AD_PREFERENCE_ID><![CDATA[1000001]]></AD_PREFERENCE_ID>
<!--AD_PREFERENCE_ID=1000001 AD_CLIENT_ID-->
<!--AD_PREFERENCE_ID=1000001-->                        <AD_CLIENT_ID><![CDATA[1000000]]></AD_CLIENT_ID>
<!--AD_PREFERENCE_ID=1000001 AD_ORG_ID-->
<!--AD_PREFERENCE_ID=1000001-->                        <AD_ORG_ID><![CDATA[0]]></AD_ORG_ID>
<!--AD_PREFERENCE_ID=1000001 ISACTIVE-->
<!--AD_PREFERENCE_ID=1000001-->                        <ISACTIVE><![CDATA[Y]]></ISACTIVE>
<!--AD_PREFERENCE_ID=1000001 CREATED-->
<!--AD_PREFERENCE_ID=1000001-->                        <CREATED><![CDATA[2006-03-14 20:51:17.0]]></CREATED>
<!--AD_PREFERENCE_ID=1000001 CREATEDBY-->
<!--AD_PREFERENCE_ID=1000001-->                        <CREATEDBY><![CDATA[0]]></CREATEDBY>
<!--AD_PREFERENCE_ID=1000001 UPDATED-->
<!--AD_PREFERENCE_ID=1000001-->                        <UPDATED><![CDATA[2006-03-14 20:51:17.0]]></UPDATED>
<!--AD_PREFERENCE_ID=1000001 UPDATEDBY-->
<!--AD_PREFERENCE_ID=1000001-->                        <UPDATEDBY><![CDATA[0]]></UPDATEDBY>
<!--AD_PREFERENCE_ID=1000001 ATTRIBUTE-->
<!--AD_PREFERENCE_ID=1000001-->                        <ATTRIBUTE><![CDATA[C_Country_ID]]></ATTRIBUTE>
<!--AD_PREFERENCE_ID=1000001 VALUE-->
<!--AD_PREFERENCE_ID=1000001-->                        <VALUE><![CDATA[106]]></VALUE>
<!--AD_PREFERENCE_ID=1000001-->                    </AD_PREFERENCE>
<!--AD_PREFERENCE_ID=1000002-->                    <AD_PREFERENCE>
<!--AD_PREFERENCE_ID=1000002 AD_PREFERENCE_ID-->
<!--AD_PREFERENCE_ID=1000002-->                        <AD_PREFERENCE_ID><![CDATA[1000002]]></AD_PREFERENCE_ID>
<!--AD_PREFERENCE_ID=1000002 AD_CLIENT_ID-->
<!--AD_PREFERENCE_ID=1000002-->                        <AD_CLIENT_ID><![CDATA[1000000]]></AD_CLIENT_ID>
<!--AD_PREFERENCE_ID=1000002 AD_ORG_ID-->
<!--AD_PREFERENCE_ID=1000002-->                        <AD_ORG_ID><![CDATA[1000000]]></AD_ORG_ID>
<!--AD_PREFERENCE_ID=1000002 ISACTIVE-->
<!--AD_PREFERENCE_ID=1000002-->                        <ISACTIVE><![CDATA[Y]]></ISACTIVE>
<!--AD_PREFERENCE_ID=1000002 CREATED-->
<!--AD_PREFERENCE_ID=1000002-->                        <CREATED><![CDATA[2006-03-15 11:09:24.0]]></CREATED>
<!--AD_PREFERENCE_ID=1000002 CREATEDBY-->
<!--AD_PREFERENCE_ID=1000002-->                        <CREATEDBY><![CDATA[1000000]]></CREATEDBY>
<!--AD_PREFERENCE_ID=1000002 UPDATED-->
<!--AD_PREFERENCE_ID=1000002-->                        <UPDATED><![CDATA[2006-03-15 11:09:24.0]]></UPDATED>
<!--AD_PREFERENCE_ID=1000002 UPDATEDBY-->
<!--AD_PREFERENCE_ID=1000002-->                        <UPDATEDBY><![CDATA[1000000]]></UPDATEDBY>
<!--AD_PREFERENCE_ID=1000002 AD_USER_ID-->
<!--AD_PREFERENCE_ID=1000002-->                        <AD_USER_ID><![CDATA[1000000]]></AD_USER_ID>
<!--AD_PREFERENCE_ID=1000002 ATTRIBUTE-->
<!--AD_PREFERENCE_ID=1000002-->                        <ATTRIBUTE><![CDATA[ShowTrl]]></ATTRIBUTE>
<!--AD_PREFERENCE_ID=1000002 VALUE-->
<!--AD_PREFERENCE_ID=1000002-->                        <VALUE><![CDATA[Y]]></VALUE>
<!--AD_PREFERENCE_ID=1000002-->                    </AD_PREFERENCE>
<!--AD_PREFERENCE_ID=1000003-->                    <AD_PREFERENCE>
<!--AD_PREFERENCE_ID=1000003 AD_PREFERENCE_ID-->
<!--AD_PREFERENCE_ID=1000003-->                        <AD_PREFERENCE_ID><![CDATA[1000003]]></AD_PREFERENCE_ID>
<!--AD_PREFERENCE_ID=1000003 AD_CLIENT_ID-->
<!--AD_PREFERENCE_ID=1000003-->                        <AD_CLIENT_ID><![CDATA[1000000]]></AD_CLIENT_ID>
<!--AD_PREFERENCE_ID=1000003 AD_ORG_ID-->
<!--AD_PREFERENCE_ID=1000003-->                        <AD_ORG_ID><![CDATA[1000000]]></AD_ORG_ID>
<!--AD_PREFERENCE_ID=1000003 ISACTIVE-->
<!--AD_PREFERENCE_ID=1000003-->                        <ISACTIVE><![CDATA[Y]]></ISACTIVE>
<!--AD_PREFERENCE_ID=1000003 CREATED-->
<!--AD_PREFERENCE_ID=1000003-->                        <CREATED><![CDATA[2006-03-15 11:09:24.0]]></CREATED>
<!--AD_PREFERENCE_ID=1000003 CREATEDBY-->
<!--AD_PREFERENCE_ID=1000003-->                        <CREATEDBY><![CDATA[1000000]]></CREATEDBY>
<!--AD_PREFERENCE_ID=1000003 UPDATED-->
<!--AD_PREFERENCE_ID=1000003-->                        <UPDATED><![CDATA[2006-03-15 11:09:24.0]]></UPDATED>
<!--AD_PREFERENCE_ID=1000003 UPDATEDBY-->
<!--AD_PREFERENCE_ID=1000003-->                        <UPDATEDBY><![CDATA[1000000]]></UPDATEDBY>
<!--AD_PREFERENCE_ID=1000003 AD_USER_ID-->
<!--AD_PREFERENCE_ID=1000003-->                        <AD_USER_ID><![CDATA[1000000]]></AD_USER_ID>
<!--AD_PREFERENCE_ID=1000003 ATTRIBUTE-->
<!--AD_PREFERENCE_ID=1000003-->                        <ATTRIBUTE><![CDATA[ShowAcct]]></ATTRIBUTE>
<!--AD_PREFERENCE_ID=1000003 VALUE-->
<!--AD_PREFERENCE_ID=1000003-->                        <VALUE><![CDATA[Y]]></VALUE>
<!--AD_PREFERENCE_ID=1000003-->                    </AD_PREFERENCE>
<!--AD_PREFERENCE_ID=1000004-->                    <AD_PREFERENCE>
<!--AD_PREFERENCE_ID=1000004 AD_PREFERENCE_ID-->
<!--AD_PREFERENCE_ID=1000004-->                        <AD_PREFERENCE_ID><![CDATA[1000004]]></AD_PREFERENCE_ID>
<!--AD_PREFERENCE_ID=1000004 AD_CLIENT_ID-->
<!--AD_PREFERENCE_ID=1000004-->                        <AD_CLIENT_ID><![CDATA[1000000]]></AD_CLIENT_ID>
<!--AD_PREFERENCE_ID=1000004 AD_ORG_ID-->
<!--AD_PREFERENCE_ID=1000004-->                        <AD_ORG_ID><![CDATA[1000000]]></AD_ORG_ID>
<!--AD_PREFERENCE_ID=1000004 ISACTIVE-->
<!--AD_PREFERENCE_ID=1000004-->                        <ISACTIVE><![CDATA[Y]]></ISACTIVE>
<!--AD_PREFERENCE_ID=1000004 CREATED-->
<!--AD_PREFERENCE_ID=1000004-->                        <CREATED><![CDATA[2006-03-15 11:09:24.0]]></CREATED>
<!--AD_PREFERENCE_ID=1000004 CREATEDBY-->
<!--AD_PREFERENCE_ID=1000004-->                        <CREATEDBY><![CDATA[1000000]]></CREATEDBY>
<!--AD_PREFERENCE_ID=1000004 UPDATED-->
<!--AD_PREFERENCE_ID=1000004-->                        <UPDATED><![CDATA[2006-03-15 11:09:24.0]]></UPDATED>
<!--AD_PREFERENCE_ID=1000004 UPDATEDBY-->
<!--AD_PREFERENCE_ID=1000004-->                        <UPDATEDBY><![CDATA[1000000]]></UPDATEDBY>
<!--AD_PREFERENCE_ID=1000004 AD_USER_ID-->
<!--AD_PREFERENCE_ID=1000004-->                        <AD_USER_ID><![CDATA[1000000]]></AD_USER_ID>
<!--AD_PREFERENCE_ID=1000004 ATTRIBUTE-->
<!--AD_PREFERENCE_ID=1000004-->                        <ATTRIBUTE><![CDATA[ShowTest]]></ATTRIBUTE>
<!--AD_PREFERENCE_ID=1000004 VALUE-->
<!--AD_PREFERENCE_ID=1000004-->                        <VALUE><![CDATA[N]]></VALUE>
<!--AD_PREFERENCE_ID=1000004-->                    </AD_PREFERENCE>
<!--AD_PREFERENCE_ID=1000005-->                    <AD_PREFERENCE>
<!--AD_PREFERENCE_ID=1000005 AD_PREFERENCE_ID-->
<!--AD_PREFERENCE_ID=1000005-->                        <AD_PREFERENCE_ID><![CDATA[1000005]]></AD_PREFERENCE_ID>
<!--AD_PREFERENCE_ID=1000005 AD_CLIENT_ID-->
<!--AD_PREFERENCE_ID=1000005-->                        <AD_CLIENT_ID><![CDATA[1000000]]></AD_CLIENT_ID>
<!--AD_PREFERENCE_ID=1000005 AD_ORG_ID-->
<!--AD_PREFERENCE_ID=1000005-->                        <AD_ORG_ID><![CDATA[1000000]]></AD_ORG_ID>
<!--AD_PREFERENCE_ID=1000005 ISACTIVE-->
<!--AD_PREFERENCE_ID=1000005-->                        <ISACTIVE><![CDATA[Y]]></ISACTIVE>
<!--AD_PREFERENCE_ID=1000005 CREATED-->
<!--AD_PREFERENCE_ID=1000005-->                        <CREATED><![CDATA[2006-03-22 10:50:19.0]]></CREATED>
<!--AD_PREFERENCE_ID=1000005 CREATEDBY-->
<!--AD_PREFERENCE_ID=1000005-->                        <CREATEDBY><![CDATA[100]]></CREATEDBY>
<!--AD_PREFERENCE_ID=1000005 UPDATED-->
<!--AD_PREFERENCE_ID=1000005-->                        <UPDATED><![CDATA[2006-03-22 10:50:45.0]]></UPDATED>
<!--AD_PREFERENCE_ID=1000005 UPDATEDBY-->
<!--AD_PREFERENCE_ID=1000005-->                        <UPDATEDBY><![CDATA[100]]></UPDATEDBY>
<!--AD_PREFERENCE_ID=1000005 AD_USER_ID-->
<!--AD_PREFERENCE_ID=1000005-->                        <AD_USER_ID><![CDATA[100]]></AD_USER_ID>
<!--AD_PREFERENCE_ID=1000005 ATTRIBUTE-->
<!--AD_PREFERENCE_ID=1000005-->                        <ATTRIBUTE><![CDATA[ShowTrl]]></ATTRIBUTE>
<!--AD_PREFERENCE_ID=1000005 VALUE-->
<!--AD_PREFERENCE_ID=1000005-->                        <VALUE><![CDATA[Y]]></VALUE>
<!--AD_PREFERENCE_ID=1000005-->                    </AD_PREFERENCE>
<!--AD_PREFERENCE_ID=1000006-->                    <AD_PREFERENCE>
<!--AD_PREFERENCE_ID=1000006 AD_PREFERENCE_ID-->
<!--AD_PREFERENCE_ID=1000006-->                        <AD_PREFERENCE_ID><![CDATA[1000006]]></AD_PREFERENCE_ID>
<!--AD_PREFERENCE_ID=1000006 AD_CLIENT_ID-->
<!--AD_PREFERENCE_ID=1000006-->                        <AD_CLIENT_ID><![CDATA[1000000]]></AD_CLIENT_ID>
<!--AD_PREFERENCE_ID=1000006 AD_ORG_ID-->
<!--AD_PREFERENCE_ID=1000006-->                        <AD_ORG_ID><![CDATA[1000000]]></AD_ORG_ID>
<!--AD_PREFERENCE_ID=1000006 ISACTIVE-->
<!--AD_PREFERENCE_ID=1000006-->                        <ISACTIVE><![CDATA[Y]]></ISACTIVE>
<!--AD_PREFERENCE_ID=1000006 CREATED-->
<!--AD_PREFERENCE_ID=1000006-->                        <CREATED><![CDATA[2006-03-22 10:50:19.0]]></CREATED>
<!--AD_PREFERENCE_ID=1000006 CREATEDBY-->
<!--AD_PREFERENCE_ID=1000006-->                        <CREATEDBY><![CDATA[100]]></CREATEDBY>
<!--AD_PREFERENCE_ID=1000006 UPDATED-->
<!--AD_PREFERENCE_ID=1000006-->                        <UPDATED><![CDATA[2006-03-22 10:50:45.0]]></UPDATED>
<!--AD_PREFERENCE_ID=1000006 UPDATEDBY-->
<!--AD_PREFERENCE_ID=1000006-->                        <UPDATEDBY><![CDATA[100]]></UPDATEDBY>
<!--AD_PREFERENCE_ID=1000006 AD_USER_ID-->
<!--AD_PREFERENCE_ID=1000006-->                        <AD_USER_ID><![CDATA[100]]></AD_USER_ID>
<!--AD_PREFERENCE_ID=1000006 ATTRIBUTE-->
<!--AD_PREFERENCE_ID=1000006-->                        <ATTRIBUTE><![CDATA[ShowAcct]]></ATTRIBUTE>
<!--AD_PREFERENCE_ID=1000006 VALUE-->
<!--AD_PREFERENCE_ID=1000006-->                        <VALUE><![CDATA[Y]]></VALUE>
<!--AD_PREFERENCE_ID=1000006-->                    </AD_PREFERENCE>
<!--AD_PREFERENCE_ID=1000007-->                    <AD_PREFERENCE>
<!--AD_PREFERENCE_ID=1000007 AD_PREFERENCE_ID-->
<!--AD_PREFERENCE_ID=1000007-->                        <AD_PREFERENCE_ID><![CDATA[1000007]]></AD_PREFERENCE_ID>
<!--AD_PREFERENCE_ID=1000007 AD_CLIENT_ID-->
<!--AD_PREFERENCE_ID=1000007-->                        <AD_CLIENT_ID><![CDATA[1000000]]></AD_CLIENT_ID>
<!--AD_PREFERENCE_ID=1000007 AD_ORG_ID-->
<!--AD_PREFERENCE_ID=1000007-->                        <AD_ORG_ID><![CDATA[1000000]]></AD_ORG_ID>
<!--AD_PREFERENCE_ID=1000007 ISACTIVE-->
<!--AD_PREFERENCE_ID=1000007-->                        <ISACTIVE><![CDATA[Y]]></ISACTIVE>
<!--AD_PREFERENCE_ID=1000007 CREATED-->
<!--AD_PREFERENCE_ID=1000007-->                        <CREATED><![CDATA[2006-03-22 10:50:19.0]]></CREATED>
<!--AD_PREFERENCE_ID=1000007 CREATEDBY-->
<!--AD_PREFERENCE_ID=1000007-->                        <CREATEDBY><![CDATA[100]]></CREATEDBY>
<!--AD_PREFERENCE_ID=1000007 UPDATED-->
<!--AD_PREFERENCE_ID=1000007-->                        <UPDATED><![CDATA[2006-03-22 10:50:45.0]]></UPDATED>
<!--AD_PREFERENCE_ID=1000007 UPDATEDBY-->
<!--AD_PREFERENCE_ID=1000007-->                        <UPDATEDBY><![CDATA[100]]></UPDATEDBY>
<!--AD_PREFERENCE_ID=1000007 AD_USER_ID-->
<!--AD_PREFERENCE_ID=1000007-->                        <AD_USER_ID><![CDATA[100]]></AD_USER_ID>
<!--AD_PREFERENCE_ID=1000007 ATTRIBUTE-->
<!--AD_PREFERENCE_ID=1000007-->                        <ATTRIBUTE><![CDATA[ShowTest]]></ATTRIBUTE>
<!--AD_PREFERENCE_ID=1000007 VALUE-->
<!--AD_PREFERENCE_ID=1000007-->                        <VALUE><![CDATA[N]]></VALUE>
<!--AD_PREFERENCE_ID=1000007-->                    </AD_PREFERENCE>
<!--AD_PREFERENCE_ID=1000008-->                    <AD_PREFERENCE>
<!--AD_PREFERENCE_ID=1000008 AD_PREFERENCE_ID-->
<!--AD_PREFERENCE_ID=1000008-->                        <AD_PREFERENCE_ID><![CDATA[1000008]]></AD_PREFERENCE_ID>
<!--AD_PREFERENCE_ID=1000008 AD_CLIENT_ID-->
<!--AD_PREFERENCE_ID=1000008-->                        <AD_CLIENT_ID><![CDATA[1000001]]></AD_CLIENT_ID>
<!--AD_PREFERENCE_ID=1000008 AD_ORG_ID-->
<!--AD_PREFERENCE_ID=1000008-->                        <AD_ORG_ID><![CDATA[0]]></AD_ORG_ID>
<!--AD_PREFERENCE_ID=1000008 ISACTIVE-->
<!--AD_PREFERENCE_ID=1000008-->                        <ISACTIVE><![CDATA[Y]]></ISACTIVE>
<!--AD_PREFERENCE_ID=1000008 CREATED-->
<!--AD_PREFERENCE_ID=1000008-->                        <CREATED><![CDATA[2007-12-11 11:59:24.0]]></CREATED>
<!--AD_PREFERENCE_ID=1000008 CREATEDBY-->
<!--AD_PREFERENCE_ID=1000008-->                        <CREATEDBY><![CDATA[0]]></CREATEDBY>
<!--AD_PREFERENCE_ID=1000008 UPDATED-->
<!--AD_PREFERENCE_ID=1000008-->                        <UPDATED><![CDATA[2007-12-11 11:59:24.0]]></UPDATED>
<!--AD_PREFERENCE_ID=1000008 UPDATEDBY-->
<!--AD_PREFERENCE_ID=1000008-->                        <UPDATEDBY><![CDATA[0]]></UPDATEDBY>
<!--AD_PREFERENCE_ID=1000008 AD_WINDOW_ID-->
<!--AD_PREFERENCE_ID=1000008-->                        <AD_WINDOW_ID><![CDATA[143]]></AD_WINDOW_ID>
<!--AD_PREFERENCE_ID=1000008 ATTRIBUTE-->
<!--AD_PREFERENCE_ID=1000008-->                        <ATTRIBUTE><![CDATA[C_DocTypeTarget_ID]]></ATTRIBUTE>
<!--AD_PREFERENCE_ID=1000008 VALUE-->
<!--AD_PREFERENCE_ID=1000008-->                        <VALUE><![CDATA[1000063]]></VALUE>
<!--AD_PREFERENCE_ID=1000008-->                    </AD_PREFERENCE>
<!--AD_PREFERENCE_ID=1000009-->                    <AD_PREFERENCE>
<!--AD_PREFERENCE_ID=1000009 AD_PREFERENCE_ID-->
<!--AD_PREFERENCE_ID=1000009-->                        <AD_PREFERENCE_ID><![CDATA[1000009]]></AD_PREFERENCE_ID>
<!--AD_PREFERENCE_ID=1000009 AD_CLIENT_ID-->
<!--AD_PREFERENCE_ID=1000009-->                        <AD_CLIENT_ID><![CDATA[1000001]]></AD_CLIENT_ID>
<!--AD_PREFERENCE_ID=1000009 AD_ORG_ID-->
<!--AD_PREFERENCE_ID=1000009-->                        <AD_ORG_ID><![CDATA[0]]></AD_ORG_ID>
<!--AD_PREFERENCE_ID=1000009 ISACTIVE-->
<!--AD_PREFERENCE_ID=1000009-->                        <ISACTIVE><![CDATA[Y]]></ISACTIVE>
<!--AD_PREFERENCE_ID=1000009 CREATED-->
<!--AD_PREFERENCE_ID=1000009-->                        <CREATED><![CDATA[2007-12-11 11:59:24.0]]></CREATED>
<!--AD_PREFERENCE_ID=1000009 CREATEDBY-->
<!--AD_PREFERENCE_ID=1000009-->                        <CREATEDBY><![CDATA[0]]></CREATEDBY>
<!--AD_PREFERENCE_ID=1000009 UPDATED-->
<!--AD_PREFERENCE_ID=1000009-->                        <UPDATED><![CDATA[2007-12-11 11:59:24.0]]></UPDATED>
<!--AD_PREFERENCE_ID=1000009 UPDATEDBY-->
<!--AD_PREFERENCE_ID=1000009-->                        <UPDATEDBY><![CDATA[0]]></UPDATEDBY>
<!--AD_PREFERENCE_ID=1000009 AD_WINDOW_ID-->
<!--AD_PREFERENCE_ID=1000009-->                        <AD_WINDOW_ID><![CDATA[800004]]></AD_WINDOW_ID>
<!--AD_PREFERENCE_ID=1000009 ATTRIBUTE-->
<!--AD_PREFERENCE_ID=1000009-->                        <ATTRIBUTE><![CDATA[C_DocTypeTarget_ID]]></ATTRIBUTE>
<!--AD_PREFERENCE_ID=1000009 VALUE-->
<!--AD_PREFERENCE_ID=1000009-->                        <VALUE><![CDATA[1000062]]></VALUE>
<!--AD_PREFERENCE_ID=1000009-->                    </AD_PREFERENCE>
<!--AD_PREFERENCE_ID=1000010-->                    <AD_PREFERENCE>
<!--AD_PREFERENCE_ID=1000010 AD_PREFERENCE_ID-->
<!--AD_PREFERENCE_ID=1000010-->                        <AD_PREFERENCE_ID><![CDATA[1000010]]></AD_PREFERENCE_ID>
<!--AD_PREFERENCE_ID=1000010 AD_CLIENT_ID-->
<!--AD_PREFERENCE_ID=1000010-->                        <AD_CLIENT_ID><![CDATA[1000001]]></AD_CLIENT_ID>
<!--AD_PREFERENCE_ID=1000010 AD_ORG_ID-->
<!--AD_PREFERENCE_ID=1000010-->                        <AD_ORG_ID><![CDATA[0]]></AD_ORG_ID>
<!--AD_PREFERENCE_ID=1000010 ISACTIVE-->
<!--AD_PREFERENCE_ID=1000010-->                        <ISACTIVE><![CDATA[Y]]></ISACTIVE>
<!--AD_PREFERENCE_ID=1000010 CREATED-->
<!--AD_PREFERENCE_ID=1000010-->                        <CREATED><![CDATA[2007-12-11 11:59:25.0]]></CREATED>
<!--AD_PREFERENCE_ID=1000010 CREATEDBY-->
<!--AD_PREFERENCE_ID=1000010-->                        <CREATEDBY><![CDATA[0]]></CREATEDBY>
<!--AD_PREFERENCE_ID=1000010 UPDATED-->
<!--AD_PREFERENCE_ID=1000010-->                        <UPDATED><![CDATA[2007-12-11 11:59:25.0]]></UPDATED>
<!--AD_PREFERENCE_ID=1000010 UPDATEDBY-->
<!--AD_PREFERENCE_ID=1000010-->                        <UPDATEDBY><![CDATA[0]]></UPDATEDBY>
<!--AD_PREFERENCE_ID=1000010 ATTRIBUTE-->
<!--AD_PREFERENCE_ID=1000010-->                        <ATTRIBUTE><![CDATA[C_Country_ID]]></ATTRIBUTE>
<!--AD_PREFERENCE_ID=1000010 VALUE-->
<!--AD_PREFERENCE_ID=1000010-->                        <VALUE><![CDATA[100]]></VALUE>
<!--AD_PREFERENCE_ID=1000010-->                    </AD_PREFERENCE>
<!--
************************
1. End of Custom Range.
************************
-->
</data>
