<?xml version='1.0' encoding='UTF-8'?>
<data>
  <C_ORDERLINE C_ORDERLINE_ID="1000000" AD_CLIENT_ID="1000000" AD_ORG_ID="1000000" ISACTIVE="Y" CREATED="2006-03-28 14:16:04.0" CREATEDBY="100" UPDATED="2006-03-31 11:37:36.0" UPDATEDBY="100" C_ORDER_ID="1000000" LINE="10" C_BPARTNER_ID="1000010" C_BPARTNER_LOCATION_ID="1000006" DATEORDERED="2006-03-28 00:00:00.0" DATEPROMISED="2006-03-28 00:00:00.0" DATEINVOICED="2006-03-31 11:37:18.0" M_PRODUCT_ID="1000000" M_WAREHOUSE_ID="1000000" DIRECTSHIP="N" C_UOM_ID="1000001" QTYORDERED="50" QTYRESERVED="0" QTYDELIVERED="50" QTYINVOICED="50" C_CURRENCY_ID="102" PRICELIST="6.25" PRICEACTUAL="5.9" PRICELIMIT="5.6" LINENETAMT="295" DISCOUNT="5.6" FREIGHTAMT="0" CHARGEAMT="0" C_TAX_ID="1000000" ISDESCRIPTION="N" PRICESTD="5.9" />
  <C_ORDERLINE C_ORDERLINE_ID="1000001" AD_CLIENT_ID="1000000" AD_ORG_ID="1000000" ISACTIVE="Y" CREATED="2006-03-29 11:45:55.0" CREATEDBY="100" UPDATED="2006-03-29 11:47:27.0" UPDATEDBY="100" C_ORDER_ID="1000001" LINE="10" C_BPARTNER_ID="1000009" C_BPARTNER_LOCATION_ID="1000005" DATEORDERED="2006-03-29 00:00:00.0" DATEPROMISED="2006-03-29 00:00:00.0" DATEINVOICED="2006-03-29 11:47:26.0" M_PRODUCT_ID="1000004" M_WAREHOUSE_ID="1000000" DIRECTSHIP="N" C_UOM_ID="100" QTYORDERED="100" QTYRESERVED="0" QTYDELIVERED="100" QTYINVOICED="100" C_CURRENCY_ID="102" PRICELIST="13" PRICEACTUAL="12" PRICELIMIT="11" LINENETAMT="1200" DISCOUNT="7.69" FREIGHTAMT="0" CHARGEAMT="0" C_TAX_ID="1000000" ISDESCRIPTION="N" PRICESTD="12" />
  <C_ORDERLINE C_ORDERLINE_ID="1000002" AD_CLIENT_ID="1000000" AD_ORG_ID="1000000" ISACTIVE="Y" CREATED="2006-03-29 11:46:43.0" CREATEDBY="100" UPDATED="2006-03-29 11:47:27.0" UPDATEDBY="100" C_ORDER_ID="1000001" LINE="20" C_BPARTNER_ID="1000009" C_BPARTNER_LOCATION_ID="1000005" DATEORDERED="2006-03-29 00:00:00.0" DATEPROMISED="2006-03-29 00:00:00.0" DATEINVOICED="2006-03-29 11:47:26.0" M_PRODUCT_ID="1000005" M_WAREHOUSE_ID="1000000" DIRECTSHIP="N" C_UOM_ID="100" QTYORDERED="50" QTYRESERVED="0" QTYDELIVERED="50" QTYINVOICED="50" C_CURRENCY_ID="102" PRICELIST="42" PRICEACTUAL="37.8" PRICELIMIT="36" LINENETAMT="1890" DISCOUNT="10" FREIGHTAMT="0" CHARGEAMT="0" C_TAX_ID="1000000" ISDESCRIPTION="N" PRICESTD="37.8" />
  <C_ORDERLINE C_ORDERLINE_ID="1000003" AD_CLIENT_ID="1000000" AD_ORG_ID="1000000" ISACTIVE="Y" CREATED="2006-03-29 12:22:22.0" CREATEDBY="100" UPDATED="2006-03-31 11:37:35.0" UPDATEDBY="100" C_ORDER_ID="1000002" LINE="10" C_BPARTNER_ID="1000006" C_BPARTNER_LOCATION_ID="1000011" DATEORDERED="2006-03-29 00:00:00.0" DATEPROMISED="2006-03-29 00:00:00.0" DATEINVOICED="2006-03-31 11:37:05.0" M_PRODUCT_ID="1000005" M_WAREHOUSE_ID="1000000" DIRECTSHIP="N" C_UOM_ID="100" QTYORDERED="10" QTYRESERVED="0" QTYDELIVERED="10" QTYINVOICED="10" M_SHIPPER_ID="1000000" C_CURRENCY_ID="102" PRICELIST="37.8" PRICEACTUAL="34.02" PRICELIMIT="32.4" LINENETAMT="340.2" DISCOUNT="10" FREIGHTAMT="0" CHARGEAMT="0" C_TAX_ID="1000000" ISDESCRIPTION="N" PRICESTD="34.02" />
  <C_ORDERLINE C_ORDERLINE_ID="1000004" AD_CLIENT_ID="1000000" AD_ORG_ID="1000000" ISACTIVE="Y" CREATED="2006-03-29 13:10:29.0" CREATEDBY="100" UPDATED="2006-04-03 12:11:11.0" UPDATEDBY="100" C_ORDER_ID="1000003" LINE="10" C_BPARTNER_ID="1000004" C_BPARTNER_LOCATION_ID="1000001" DATEORDERED="2006-03-29 00:00:00.0" DATEPROMISED="2006-03-29 00:00:00.0" DATEINVOICED="2006-04-03 00:00:00.0" M_PRODUCT_ID="1000011" M_WAREHOUSE_ID="1000000" DIRECTSHIP="N" C_UOM_ID="100" QTYORDERED="5" QTYRESERVED="0" QTYDELIVERED="5" QTYINVOICED="5" C_CURRENCY_ID="102" PRICELIST="13" PRICEACTUAL="12.5" PRICELIMIT="12" LINENETAMT="62.5" DISCOUNT="3.85" FREIGHTAMT="0" CHARGEAMT="0" C_TAX_ID="1000000" ISDESCRIPTION="N" PRICESTD="12.5" />
  <C_ORDERLINE C_ORDERLINE_ID="1000005" AD_CLIENT_ID="1000000" AD_ORG_ID="1000000" ISACTIVE="Y" CREATED="2006-03-29 14:10:41.0" CREATEDBY="100" UPDATED="2006-03-29 14:12:01.0" UPDATEDBY="100" C_ORDER_ID="1000004" LINE="10" C_BPARTNER_ID="1000007" C_BPARTNER_LOCATION_ID="1000003" DATEORDERED="2006-03-29 00:00:00.0" DATEPROMISED="2006-03-29 00:00:00.0" M_PRODUCT_ID="1000015" M_WAREHOUSE_ID="1000000" DIRECTSHIP="N" C_UOM_ID="100" QTYORDERED="50" QTYRESERVED="-50" QTYDELIVERED="0" QTYINVOICED="0" C_CURRENCY_ID="102" PRICELIST="50" PRICEACTUAL="45" PRICELIMIT="58" LINENETAMT="2250" DISCOUNT="10" FREIGHTAMT="0" CHARGEAMT="0" C_TAX_ID="1000000" ISDESCRIPTION="N" PRICESTD="45" />
  <C_ORDERLINE C_ORDERLINE_ID="1000006" AD_CLIENT_ID="1000000" AD_ORG_ID="1000000" ISACTIVE="Y" CREATED="2006-03-30 10:13:30.0" CREATEDBY="100" UPDATED="2006-04-01 10:59:00.0" UPDATEDBY="100" C_ORDER_ID="1000005" LINE="10" C_BPARTNER_ID="1000004" C_BPARTNER_LOCATION_ID="1000001" DATEORDERED="2006-03-30 00:00:00.0" DATEPROMISED="2006-03-30 00:00:00.0" DATEINVOICED="2006-03-30 00:00:00.0" M_PRODUCT_ID="1000005" M_WAREHOUSE_ID="1000000" DIRECTSHIP="N" C_UOM_ID="100" QTYORDERED="150" QTYRESERVED="0" QTYDELIVERED="150" QTYINVOICED="150" C_CURRENCY_ID="102" PRICELIST="42" PRICEACTUAL="37.8" PRICELIMIT="36" LINENETAMT="5670" DISCOUNT="10" FREIGHTAMT="0" CHARGEAMT="0" C_TAX_ID="1000000" M_ATTRIBUTESETINSTANCE_ID="1000008" ISDESCRIPTION="N" PRICESTD="37.8" />
  <C_ORDERLINE C_ORDERLINE_ID="1000007" AD_CLIENT_ID="1000000" AD_ORG_ID="1000000" ISACTIVE="Y" CREATED="2006-03-30 10:16:24.0" CREATEDBY="100" UPDATED="2006-04-01 10:59:00.0" UPDATEDBY="100" C_ORDER_ID="1000005" LINE="20" C_BPARTNER_ID="1000004" C_BPARTNER_LOCATION_ID="1000001" DATEORDERED="2006-03-30 00:00:00.0" DATEPROMISED="2006-03-30 00:00:00.0" DATEINVOICED="2006-03-30 00:00:00.0" M_PRODUCT_ID="1000007" M_WAREHOUSE_ID="1000000" DIRECTSHIP="N" C_UOM_ID="1000002" QTYORDERED="50" QTYRESERVED="0" QTYDELIVERED="50" QTYINVOICED="50" C_CURRENCY_ID="102" PRICELIST="0.63" PRICEACTUAL="0.6" PRICELIMIT="0.55" LINENETAMT="30" DISCOUNT="4.76" FREIGHTAMT="0" CHARGEAMT="0" C_TAX_ID="1000000" ISDESCRIPTION="N" PRICESTD="0.6" />
  <C_ORDERLINE C_ORDERLINE_ID="1000008" AD_CLIENT_ID="1000000" AD_ORG_ID="1000000" ISACTIVE="Y" CREATED="2006-03-31 11:03:35.0" CREATEDBY="100" UPDATED="2006-03-31 17:47:50.0" UPDATEDBY="100" C_ORDER_ID="1000006" LINE="10" C_BPARTNER_ID="1000008" C_BPARTNER_LOCATION_ID="1000004" DATEORDERED="2006-03-31 00:00:00.0" DATEPROMISED="2006-03-31 00:00:00.0" DESCRIPTION="Camisetas de talla grande" M_PRODUCT_ID="1000004" M_WAREHOUSE_ID="1000000" DIRECTSHIP="N" C_UOM_ID="100" QTYORDERED="100" QTYRESERVED="-100" QTYDELIVERED="0" QTYINVOICED="0" C_CURRENCY_ID="102" PRICELIST="10" PRICEACTUAL="9" PRICELIMIT="12" LINENETAMT="900" DISCOUNT="10" FREIGHTAMT="0" CHARGEAMT="0" C_TAX_ID="1000000" ISDESCRIPTION="N" PRICESTD="9" />
  <C_ORDERLINE C_ORDERLINE_ID="1000009" AD_CLIENT_ID="1000000" AD_ORG_ID="1000000" ISACTIVE="Y" CREATED="2006-03-31 11:20:18.0" CREATEDBY="100" UPDATED="2006-04-03 11:27:46.0" UPDATEDBY="100" C_ORDER_ID="1000007" LINE="10" C_BPARTNER_ID="1000009" C_BPARTNER_LOCATION_ID="1000005" DATEORDERED="2006-03-31 00:00:00.0" DATEPROMISED="2006-03-31 00:00:00.0" DATEINVOICED="2006-04-03 00:00:00.0" M_PRODUCT_ID="1000014" M_WAREHOUSE_ID="1000000" DIRECTSHIP="N" C_UOM_ID="1000002" QTYORDERED="50" QTYRESERVED="0" QTYDELIVERED="50" QTYINVOICED="50" C_CURRENCY_ID="102" PRICELIST="1" PRICEACTUAL="1" PRICELIMIT="1" LINENETAMT="50" DISCOUNT="0" FREIGHTAMT="0" CHARGEAMT="0" C_TAX_ID="1000000" ISDESCRIPTION="N" PRICESTD="1" />
  <C_ORDERLINE C_ORDERLINE_ID="1000010" AD_CLIENT_ID="1000000" AD_ORG_ID="1000000" ISACTIVE="Y" CREATED="2006-03-31 11:20:36.0" CREATEDBY="100" UPDATED="2006-04-03 11:27:46.0" UPDATEDBY="100" C_ORDER_ID="1000007" LINE="20" C_BPARTNER_ID="1000009" C_BPARTNER_LOCATION_ID="1000005" DATEORDERED="2006-03-31 00:00:00.0" DATEPROMISED="2006-03-31 00:00:00.0" DATEINVOICED="2006-04-03 00:00:00.0" M_PRODUCT_ID="1000007" M_WAREHOUSE_ID="1000000" DIRECTSHIP="N" C_UOM_ID="1000002" QTYORDERED="40" QTYRESERVED="0" QTYDELIVERED="40" QTYINVOICED="40" C_CURRENCY_ID="102" PRICELIST="0.63" PRICEACTUAL="0.6" PRICELIMIT="0.55" LINENETAMT="24" DISCOUNT="4.76" FREIGHTAMT="0" CHARGEAMT="0" C_TAX_ID="1000000" ISDESCRIPTION="N" PRICESTD="0.6" />
  <C_ORDERLINE C_ORDERLINE_ID="1000011" AD_CLIENT_ID="1000000" AD_ORG_ID="1000000" ISACTIVE="Y" CREATED="2006-03-31 11:20:52.0" CREATEDBY="100" UPDATED="2006-04-03 11:27:46.0" UPDATEDBY="100" C_ORDER_ID="1000007" LINE="30" C_BPARTNER_ID="1000009" C_BPARTNER_LOCATION_ID="1000005" DATEORDERED="2006-03-31 00:00:00.0" DATEPROMISED="2006-03-31 00:00:00.0" DATEINVOICED="2006-04-03 00:00:00.0" M_PRODUCT_ID="1000006" M_WAREHOUSE_ID="1000000" DIRECTSHIP="N" C_UOM_ID="100" QTYORDERED="1" QTYRESERVED="0" QTYDELIVERED="1" QTYINVOICED="1" C_CURRENCY_ID="102" PRICELIST="37" PRICEACTUAL="35" PRICELIMIT="33.5" LINENETAMT="35" DISCOUNT="5.41" FREIGHTAMT="0" CHARGEAMT="0" C_TAX_ID="1000000" ISDESCRIPTION="N" PRICESTD="35" />
  <C_ORDERLINE C_ORDERLINE_ID="1000012" AD_CLIENT_ID="1000000" AD_ORG_ID="1000000" ISACTIVE="Y" CREATED="2006-03-31 11:22:32.0" CREATEDBY="100" UPDATED="2006-04-03 12:08:28.0" UPDATEDBY="100" C_ORDER_ID="1000008" LINE="10" C_BPARTNER_ID="1000005" C_BPARTNER_LOCATION_ID="1000002" DATEORDERED="2006-03-31 00:00:00.0" DATEPROMISED="2006-03-31 00:00:00.0" DATEINVOICED="2006-04-03 00:00:00.0" M_PRODUCT_ID="1000018" M_WAREHOUSE_ID="1000000" DIRECTSHIP="N" C_UOM_ID="100" QTYORDERED="150" QTYRESERVED="0" QTYDELIVERED="150" QTYINVOICED="150" C_CURRENCY_ID="102" PRICELIST="12" PRICEACTUAL="10.8" PRICELIMIT="12" LINENETAMT="1620" DISCOUNT="10" FREIGHTAMT="0" CHARGEAMT="0" C_TAX_ID="1000000" ISDESCRIPTION="N" M_OFFER_ID="1000000" PRICESTD="12" />
  <C_ORDERLINE C_ORDERLINE_ID="1000013" AD_CLIENT_ID="1000000" AD_ORG_ID="1000000" ISACTIVE="Y" CREATED="2006-03-31 11:22:47.0" CREATEDBY="100" UPDATED="2006-04-03 12:08:28.0" UPDATEDBY="100" C_ORDER_ID="1000008" LINE="20" C_BPARTNER_ID="1000005" C_BPARTNER_LOCATION_ID="1000002" DATEORDERED="2006-03-31 00:00:00.0" DATEPROMISED="2006-03-31 00:00:00.0" DATEINVOICED="2006-04-03 00:00:00.0" M_PRODUCT_ID="1000017" M_WAREHOUSE_ID="1000000" DIRECTSHIP="N" C_UOM_ID="100" QTYORDERED="250" QTYRESERVED="0" QTYDELIVERED="250" QTYINVOICED="250" C_CURRENCY_ID="102" PRICELIST="13" PRICEACTUAL="11.7" PRICELIMIT="13" LINENETAMT="2925" DISCOUNT="10" FREIGHTAMT="0" CHARGEAMT="0" C_TAX_ID="1000000" ISDESCRIPTION="N" M_OFFER_ID="1000000" PRICESTD="13" />
  <C_ORDERLINE C_ORDERLINE_ID="1000014" AD_CLIENT_ID="1000000" AD_ORG_ID="1000000" ISACTIVE="Y" CREATED="2006-03-31 11:36:28.0" CREATEDBY="100" UPDATED="2006-04-03 11:35:56.0" UPDATEDBY="100" C_ORDER_ID="1000009" LINE="10" C_BPARTNER_ID="1000016" C_BPARTNER_LOCATION_ID="1000013" DATEORDERED="2006-03-31 00:00:00.0" DATEPROMISED="2006-03-31 00:00:00.0" DATEINVOICED="2006-04-01 20:12:45.0" M_PRODUCT_ID="1000011" M_WAREHOUSE_ID="1000000" DIRECTSHIP="N" C_UOM_ID="100" QTYORDERED="15" QTYRESERVED="0" QTYDELIVERED="15" QTYINVOICED="15" C_CURRENCY_ID="102" PRICELIST="13" PRICEACTUAL="12.5" PRICELIMIT="12" LINENETAMT="187.5" DISCOUNT="3.85" FREIGHTAMT="0" CHARGEAMT="0" C_TAX_ID="1000000" ISDESCRIPTION="N" PRICESTD="12.5" />
  <C_ORDERLINE C_ORDERLINE_ID="1000015" AD_CLIENT_ID="1000000" AD_ORG_ID="1000000" ISACTIVE="Y" CREATED="2006-03-31 13:29:17.0" CREATEDBY="100" UPDATED="2006-04-01 10:59:01.0" UPDATEDBY="100" C_ORDER_ID="1000010" LINE="10" C_BPARTNER_ID="1000006" C_BPARTNER_LOCATION_ID="1000011" DATEORDERED="2006-03-31 00:00:00.0" DATEPROMISED="2006-03-31 00:00:00.0" DATEINVOICED="2006-03-31 13:37:32.0" M_PRODUCT_ID="1000004" M_WAREHOUSE_ID="1000000" DIRECTSHIP="N" C_UOM_ID="100" QTYORDERED="13" QTYRESERVED="0" QTYDELIVERED="13" QTYINVOICED="13" C_CURRENCY_ID="102" PRICELIST="11.7" PRICEACTUAL="10.8" PRICELIMIT="9.9" LINENETAMT="140.4" DISCOUNT="7.69" FREIGHTAMT="0" CHARGEAMT="0" C_TAX_ID="1000000" ISDESCRIPTION="N" PRICESTD="10.8" />
  <C_ORDERLINE C_ORDERLINE_ID="1000016" AD_CLIENT_ID="1000000" AD_ORG_ID="1000000" ISACTIVE="Y" CREATED="2006-03-31 13:35:23.0" CREATEDBY="100" UPDATED="2006-10-19 15:52:57.0" UPDATEDBY="100" C_ORDER_ID="1000011" LINE="10" C_BPARTNER_ID="1000010" C_BPARTNER_LOCATION_ID="1000006" DATEORDERED="2006-03-31 00:00:00.0" DATEPROMISED="2006-03-31 00:00:00.0" DATEINVOICED="2006-03-31 00:00:00.0" M_PRODUCT_ID="1000000" M_WAREHOUSE_ID="1000000" DIRECTSHIP="N" C_UOM_ID="1000001" QTYORDERED="150" QTYRESERVED="0" QTYDELIVERED="150" QTYINVOICED="150" C_CURRENCY_ID="102" PRICELIST="6.25" PRICEACTUAL="5.9" PRICELIMIT="5.6" LINENETAMT="885" DISCOUNT="5.6" FREIGHTAMT="0" CHARGEAMT="0" C_TAX_ID="1000000" M_ATTRIBUTESETINSTANCE_ID="1000003" ISDESCRIPTION="N" LASTPRICESO="5.9" PRICESTD="5.9" />
  <C_ORDERLINE C_ORDERLINE_ID="1000017" AD_CLIENT_ID="1000000" AD_ORG_ID="1000000" ISACTIVE="Y" CREATED="2006-03-31 13:36:07.0" CREATEDBY="100" UPDATED="2006-10-19 15:52:57.0" UPDATEDBY="100" C_ORDER_ID="1000011" LINE="20" C_BPARTNER_ID="1000010" C_BPARTNER_LOCATION_ID="1000006" DATEORDERED="2006-03-31 00:00:00.0" DATEPROMISED="2006-03-31 00:00:00.0" DATEINVOICED="2006-03-31 00:00:00.0" M_PRODUCT_ID="1000000" M_WAREHOUSE_ID="1000000" DIRECTSHIP="N" C_UOM_ID="1000001" QTYORDERED="12" QTYRESERVED="0" QTYDELIVERED="12" QTYINVOICED="12" C_CURRENCY_ID="102" PRICELIST="6.25" PRICEACTUAL="5.9" PRICELIMIT="5.6" LINENETAMT="70.8" DISCOUNT="5.6" FREIGHTAMT="0" CHARGEAMT="0" C_TAX_ID="1000000" M_ATTRIBUTESETINSTANCE_ID="1000009" ISDESCRIPTION="N" LASTPRICESO="5.9" PRICESTD="5.9" />
  <C_ORDERLINE C_ORDERLINE_ID="1000018" AD_CLIENT_ID="1000000" AD_ORG_ID="1000000" ISACTIVE="Y" CREATED="2006-03-31 17:36:26.0" CREATEDBY="100" UPDATED="2006-03-31 17:47:22.0" UPDATEDBY="100" C_ORDER_ID="1000012" LINE="10" C_BPARTNER_ID="1000008" C_BPARTNER_LOCATION_ID="1000004" DATEORDERED="2006-03-31 00:00:00.0" DATEPROMISED="2006-03-31 00:00:00.0" M_PRODUCT_ID="1000009" M_WAREHOUSE_ID="1000000" DIRECTSHIP="N" C_UOM_ID="100" QTYORDERED="500" QTYRESERVED="-500" QTYDELIVERED="0" QTYINVOICED="0" C_CURRENCY_ID="102" PRICELIST="5" PRICEACTUAL="4.5" PRICELIMIT="5.4" LINENETAMT="2250" DISCOUNT="10" FREIGHTAMT="0" CHARGEAMT="0" C_TAX_ID="1000000" ISDESCRIPTION="N" PRICESTD="4.5" />
  <C_ORDERLINE C_ORDERLINE_ID="1000019" AD_CLIENT_ID="1000000" AD_ORG_ID="1000000" ISACTIVE="Y" CREATED="2006-03-31 17:36:52.0" CREATEDBY="100" UPDATED="2006-03-31 17:47:22.0" UPDATEDBY="100" C_ORDER_ID="1000012" LINE="20" C_BPARTNER_ID="1000008" C_BPARTNER_LOCATION_ID="1000004" DATEORDERED="2006-03-31 00:00:00.0" DATEPROMISED="2006-03-31 00:00:00.0" M_PRODUCT_ID="1000010" M_WAREHOUSE_ID="1000000" DIRECTSHIP="N" C_UOM_ID="100" QTYORDERED="1" QTYRESERVED="-1" QTYDELIVERED="0" QTYINVOICED="0" C_CURRENCY_ID="102" PRICELIST="1" PRICEACTUAL="0.94" PRICELIMIT="1.11" LINENETAMT="0.94" DISCOUNT="6" FREIGHTAMT="0" CHARGEAMT="0" C_TAX_ID="1000000" ISDESCRIPTION="N" PRICESTD="0.94" />
  <C_ORDERLINE C_ORDERLINE_ID="1000020" AD_CLIENT_ID="1000000" AD_ORG_ID="1000000" ISACTIVE="Y" CREATED="2006-03-31 17:54:18.0" CREATEDBY="100" UPDATED="2006-03-31 17:58:03.0" UPDATEDBY="100" C_ORDER_ID="1000013" LINE="10" C_BPARTNER_ID="1000007" C_BPARTNER_LOCATION_ID="1000003" DATEORDERED="2006-03-31 00:00:00.0" DATEPROMISED="2006-03-31 00:00:00.0" M_PRODUCT_ID="1000005" M_WAREHOUSE_ID="1000000" DIRECTSHIP="N" C_UOM_ID="100" QTYORDERED="80" QTYRESERVED="-80" QTYDELIVERED="0" QTYINVOICED="0" C_CURRENCY_ID="102" PRICELIST="30" PRICEACTUAL="27" PRICELIMIT="35" LINENETAMT="2160" DISCOUNT="10" FREIGHTAMT="0" CHARGEAMT="0" C_TAX_ID="1000000" ISDESCRIPTION="N" PRICESTD="27" />
  <C_ORDERLINE C_ORDERLINE_ID="1000021" AD_CLIENT_ID="1000000" AD_ORG_ID="1000000" ISACTIVE="Y" CREATED="2006-04-01 10:33:41.0" CREATEDBY="100" UPDATED="2006-04-03 12:03:00.0" UPDATEDBY="100" C_ORDER_ID="1000014" LINE="10" C_BPARTNER_ID="1000018" C_BPARTNER_LOCATION_ID="1000014" DATEORDERED="2006-04-01 00:00:00.0" DATEPROMISED="2006-04-01 00:00:00.0" DATEINVOICED="2006-04-03 00:00:00.0" M_PRODUCT_ID="1000014" M_WAREHOUSE_ID="1000000" DIRECTSHIP="N" C_UOM_ID="1000002" QTYORDERED="50" QTYRESERVED="0" QTYDELIVERED="50" QTYINVOICED="50" C_CURRENCY_ID="102" PRICELIST="1" PRICEACTUAL="1" PRICELIMIT="1" LINENETAMT="50" DISCOUNT="0" FREIGHTAMT="0" CHARGEAMT="0" C_TAX_ID="1000000" ISDESCRIPTION="N" PRICESTD="1" />
  <C_ORDERLINE C_ORDERLINE_ID="1000022" AD_CLIENT_ID="1000000" AD_ORG_ID="1000000" ISACTIVE="Y" CREATED="2006-04-01 10:34:13.0" CREATEDBY="100" UPDATED="2006-04-03 12:03:00.0" UPDATEDBY="100" C_ORDER_ID="1000014" LINE="20" C_BPARTNER_ID="1000018" C_BPARTNER_LOCATION_ID="1000014" DATEORDERED="2006-04-01 00:00:00.0" DATEPROMISED="2006-04-01 00:00:00.0" DATEINVOICED="2006-04-03 00:00:00.0" M_PRODUCT_ID="1000000" M_WAREHOUSE_ID="1000000" DIRECTSHIP="N" C_UOM_ID="1000001" QTYORDERED="43" QTYRESERVED="0" QTYDELIVERED="43" QTYINVOICED="43" C_CURRENCY_ID="102" PRICELIST="6.25" PRICEACTUAL="5.9" PRICELIMIT="5.6" LINENETAMT="253.7" DISCOUNT="5.6" FREIGHTAMT="0" CHARGEAMT="0" C_TAX_ID="1000000" ISDESCRIPTION="N" PRICESTD="5.9" />
  <C_ORDERLINE C_ORDERLINE_ID="1000023" AD_CLIENT_ID="1000000" AD_ORG_ID="1000000" ISACTIVE="Y" CREATED="2006-04-01 10:51:40.0" CREATEDBY="100" UPDATED="2006-12-12 12:09:14.0" UPDATEDBY="100" C_ORDER_ID="1000015" LINE="10" C_BPARTNER_ID="1000017" C_BPARTNER_LOCATION_ID="1000015" DATEORDERED="2006-04-01 00:00:00.0" DATEPROMISED="2006-04-01 00:00:00.0" DATEINVOICED="2006-04-03 00:00:00.0" M_PRODUCT_ID="1000008" M_WAREHOUSE_ID="1000000" DIRECTSHIP="N" C_UOM_ID="100" QTYORDERED="150" QTYRESERVED="0" QTYDELIVERED="150" QTYINVOICED="150" M_SHIPPER_ID="1000000" C_CURRENCY_ID="102" PRICELIST="2.59" PRICEACTUAL="2.43" PRICELIMIT="2.04" LINENETAMT="364.5" DISCOUNT="6.18" FREIGHTAMT="0" CHARGEAMT="0" C_TAX_ID="1000000" ISDESCRIPTION="N" PRICESTD="2.43" />
  <C_ORDERLINE C_ORDERLINE_ID="1000024" AD_CLIENT_ID="1000000" AD_ORG_ID="1000000" ISACTIVE="Y" CREATED="2006-04-01 10:52:59.0" CREATEDBY="100" UPDATED="2006-04-03 10:48:56.0" UPDATEDBY="100" C_ORDER_ID="1000016" LINE="10" C_BPARTNER_ID="1000004" C_BPARTNER_LOCATION_ID="1000001" DATEORDERED="2006-04-01 00:00:00.0" DATEPROMISED="2006-04-01 00:00:00.0" DATEINVOICED="2006-04-03 00:00:00.0" M_PRODUCT_ID="1000011" M_WAREHOUSE_ID="1000000" DIRECTSHIP="N" C_UOM_ID="100" QTYORDERED="23" QTYRESERVED="0" QTYDELIVERED="23" QTYINVOICED="23" C_CURRENCY_ID="102" PRICELIST="13" PRICEACTUAL="12.5" PRICELIMIT="12" LINENETAMT="287.5" DISCOUNT="3.85" FREIGHTAMT="0" CHARGEAMT="0" C_TAX_ID="1000000" ISDESCRIPTION="N" LASTPRICESO="12.5" PRICESTD="12.5" />
  <C_ORDERLINE C_ORDERLINE_ID="1000025" AD_CLIENT_ID="1000000" AD_ORG_ID="1000000" ISACTIVE="Y" CREATED="2006-04-01 10:56:43.0" CREATEDBY="100" UPDATED="2006-04-03 12:10:14.0" UPDATEDBY="100" C_ORDER_ID="1000017" LINE="10" C_BPARTNER_ID="1000005" C_BPARTNER_LOCATION_ID="1000002" DATEORDERED="2006-04-01 00:00:00.0" DATEPROMISED="2006-04-01 00:00:00.0" DATEINVOICED="2006-04-03 00:00:00.0" M_PRODUCT_ID="1000018" M_WAREHOUSE_ID="1000000" DIRECTSHIP="N" C_UOM_ID="100" QTYORDERED="35" QTYRESERVED="0" QTYDELIVERED="35" QTYINVOICED="35" C_CURRENCY_ID="102" PRICELIST="12" PRICEACTUAL="10.8" PRICELIMIT="12" LINENETAMT="378" DISCOUNT="10" FREIGHTAMT="0" CHARGEAMT="0" C_TAX_ID="1000000" ISDESCRIPTION="N" LASTPRICESO="10.8" M_OFFER_ID="1000000" PRICESTD="12" />
  <C_ORDERLINE C_ORDERLINE_ID="1000026" AD_CLIENT_ID="1000000" AD_ORG_ID="1000000" ISACTIVE="Y" CREATED="2006-04-01 10:57:21.0" CREATEDBY="100" UPDATED="2006-04-03 12:10:14.0" UPDATEDBY="100" C_ORDER_ID="1000017" LINE="20" C_BPARTNER_ID="1000005" C_BPARTNER_LOCATION_ID="1000002" DATEORDERED="2006-04-01 00:00:00.0" DATEPROMISED="2006-04-01 00:00:00.0" DATEINVOICED="2006-04-03 00:00:00.0" M_PRODUCT_ID="1000017" M_WAREHOUSE_ID="1000000" DIRECTSHIP="N" C_UOM_ID="100" QTYORDERED="65" QTYRESERVED="0" QTYDELIVERED="65" QTYINVOICED="65" C_CURRENCY_ID="102" PRICELIST="13" PRICEACTUAL="11.7" PRICELIMIT="13" LINENETAMT="760.5" DISCOUNT="10" FREIGHTAMT="0" CHARGEAMT="0" C_TAX_ID="1000000" ISDESCRIPTION="N" LASTPRICESO="11.7" M_OFFER_ID="1000000" PRICESTD="13" />
  <C_ORDERLINE C_ORDERLINE_ID="1000027" AD_CLIENT_ID="1000000" AD_ORG_ID="1000000" ISACTIVE="Y" CREATED="2006-04-01 20:17:14.0" CREATEDBY="100" UPDATED="2006-04-03 11:21:47.0" UPDATEDBY="100" C_ORDER_ID="1000018" LINE="10" C_BPARTNER_ID="1000006" C_BPARTNER_LOCATION_ID="1000011" DATEORDERED="2006-04-01 00:00:00.0" DATEPROMISED="2006-04-01 00:00:00.0" DATEINVOICED="2006-04-03 00:00:00.0" M_PRODUCT_ID="1000004" M_WAREHOUSE_ID="1000000" DIRECTSHIP="N" C_UOM_ID="100" QTYORDERED="25" QTYRESERVED="0" QTYDELIVERED="25" QTYINVOICED="25" C_CURRENCY_ID="102" PRICELIST="11.7" PRICEACTUAL="9.94" PRICELIMIT="9.9" LINENETAMT="248.5" DISCOUNT="15.08" FREIGHTAMT="0" CHARGEAMT="0" C_TAX_ID="1000000" M_ATTRIBUTESETINSTANCE_ID="1000000" ISDESCRIPTION="N" LASTPRICESO="10.8" M_OFFER_ID="1000001" PRICESTD="10.8" />
  <C_ORDERLINE C_ORDERLINE_ID="1000028" AD_CLIENT_ID="1000000" AD_ORG_ID="1000000" ISACTIVE="Y" CREATED="2006-04-01 20:22:00.0" CREATEDBY="100" UPDATED="2006-04-03 12:03:29.0" UPDATEDBY="100" C_ORDER_ID="1000019" LINE="10" C_BPARTNER_ID="1000010" C_BPARTNER_LOCATION_ID="1000006" DATEORDERED="2006-04-01 00:00:00.0" DATEPROMISED="2006-04-01 00:00:00.0" DATEINVOICED="2006-04-01 20:22:26.0" M_PRODUCT_ID="1000000" M_WAREHOUSE_ID="1000000" DIRECTSHIP="N" C_UOM_ID="1000001" QTYORDERED="2" QTYRESERVED="0" QTYDELIVERED="2" QTYINVOICED="2" C_CURRENCY_ID="102" PRICELIST="6.25" PRICEACTUAL="5.9" PRICELIMIT="5.6" LINENETAMT="11.8" DISCOUNT="5.6" FREIGHTAMT="0" CHARGEAMT="0" C_TAX_ID="1000000" M_ATTRIBUTESETINSTANCE_ID="1000003" ISDESCRIPTION="N" LASTPRICESO="5.9" PRICESTD="5.9" />
  <C_ORDERLINE C_ORDERLINE_ID="1000029" AD_CLIENT_ID="1000000" AD_ORG_ID="1000000" ISACTIVE="Y" CREATED="2006-04-01 20:56:44.0" CREATEDBY="100" UPDATED="2006-12-12 12:04:12.0" UPDATEDBY="1000000" C_ORDER_ID="1000021" LINE="10" C_BPARTNER_ID="1000009" C_BPARTNER_LOCATION_ID="1000005" DATEORDERED="2006-04-01 00:00:00.0" DATEPROMISED="2006-04-01 00:00:00.0" DATEINVOICED="2006-04-03 00:00:00.0" M_PRODUCT_ID="1000005" M_WAREHOUSE_ID="1000000" DIRECTSHIP="N" C_UOM_ID="100" QTYORDERED="1" QTYRESERVED="1" QTYDELIVERED="0" QTYINVOICED="1" C_CURRENCY_ID="102" PRICELIST="42" PRICEACTUAL="37.8" PRICELIMIT="36" LINENETAMT="37.8" DISCOUNT="10" FREIGHTAMT="0" CHARGEAMT="0" C_TAX_ID="1000000" M_ATTRIBUTESETINSTANCE_ID="1000010" ISDESCRIPTION="N" LASTPRICESO="37.8" PRICESTD="37.8" />
  <C_ORDERLINE C_ORDERLINE_ID="1000030" AD_CLIENT_ID="1000000" AD_ORG_ID="1000000" ISACTIVE="Y" CREATED="2006-04-03 10:21:42.0" CREATEDBY="100" UPDATED="2006-04-03 11:35:56.0" UPDATEDBY="100" C_ORDER_ID="1000022" LINE="10" C_BPARTNER_ID="1000016" C_BPARTNER_LOCATION_ID="1000013" DATEORDERED="2006-04-03 00:00:00.0" DATEPROMISED="2006-04-03 00:00:00.0" DATEINVOICED="2006-04-03 10:49:15.0" M_PRODUCT_ID="1000010" M_WAREHOUSE_ID="1000000" DIRECTSHIP="N" C_UOM_ID="100" QTYORDERED="1" QTYRESERVED="0" QTYDELIVERED="1" QTYINVOICED="1" C_CURRENCY_ID="102" PRICELIST="1.5" PRICEACTUAL="1.45" PRICELIMIT="1.3" LINENETAMT="1.45" DISCOUNT="3.33" FREIGHTAMT="0" CHARGEAMT="0" C_TAX_ID="1000000" ISDESCRIPTION="N" PRICESTD="1.45" />
  <C_ORDERLINE C_ORDERLINE_ID="1000031" AD_CLIENT_ID="1000000" AD_ORG_ID="1000000" ISACTIVE="Y" CREATED="2006-04-03 10:30:49.0" CREATEDBY="100" UPDATED="2006-04-03 11:45:58.0" UPDATEDBY="100" C_ORDER_ID="1000023" LINE="10" C_BPARTNER_ID="1000017" C_BPARTNER_LOCATION_ID="1000015" DATEORDERED="2006-04-03 00:00:00.0" DATEPROMISED="2006-04-03 00:00:00.0" M_PRODUCT_ID="1000009" M_WAREHOUSE_ID="1000000" DIRECTSHIP="N" C_UOM_ID="100" QTYORDERED="12" QTYRESERVED="0" QTYDELIVERED="12" QTYINVOICED="0" C_CURRENCY_ID="102" PRICELIST="6" PRICEACTUAL="5.8" PRICELIMIT="5.5" LINENETAMT="69.6" DISCOUNT="3.33" FREIGHTAMT="0" CHARGEAMT="0" C_TAX_ID="1000000" ISDESCRIPTION="N" PRICESTD="5.8" />
  <C_ORDERLINE C_ORDERLINE_ID="1000032" AD_CLIENT_ID="1000000" AD_ORG_ID="1000000" ISACTIVE="Y" CREATED="2006-04-03 10:31:00.0" CREATEDBY="100" UPDATED="2006-04-03 11:45:58.0" UPDATEDBY="100" C_ORDER_ID="1000023" LINE="20" C_BPARTNER_ID="1000017" C_BPARTNER_LOCATION_ID="1000015" DATEORDERED="2006-04-03 00:00:00.0" DATEPROMISED="2006-04-03 00:00:00.0" M_PRODUCT_ID="1000010" M_WAREHOUSE_ID="1000000" DIRECTSHIP="N" C_UOM_ID="100" QTYORDERED="13" QTYRESERVED="0" QTYDELIVERED="13" QTYINVOICED="0" C_CURRENCY_ID="102" PRICELIST="1.5" PRICEACTUAL="1.45" PRICELIMIT="1.3" LINENETAMT="18.85" DISCOUNT="3.33" FREIGHTAMT="0" CHARGEAMT="0" C_TAX_ID="1000000" ISDESCRIPTION="N" PRICESTD="1.45" />
  <C_ORDERLINE C_ORDERLINE_ID="1000033" AD_CLIENT_ID="1000000" AD_ORG_ID="1000000" ISACTIVE="Y" CREATED="2006-04-03 10:32:20.0" CREATEDBY="100" UPDATED="2006-04-03 11:28:12.0" UPDATEDBY="100" C_ORDER_ID="1000024" LINE="10" C_BPARTNER_ID="1000004" C_BPARTNER_LOCATION_ID="1000001" DATEORDERED="2006-04-03 00:00:00.0" DATEPROMISED="2006-04-03 00:00:00.0" DATEINVOICED="2006-04-03 10:32:50.0" M_PRODUCT_ID="1000011" M_WAREHOUSE_ID="1000000" DIRECTSHIP="N" C_UOM_ID="100" QTYORDERED="24" QTYRESERVED="0" QTYDELIVERED="24" QTYINVOICED="24" C_CURRENCY_ID="102" PRICELIST="13" PRICEACTUAL="12.5" PRICELIMIT="12" LINENETAMT="300" DISCOUNT="3.85" FREIGHTAMT="0" CHARGEAMT="0" C_TAX_ID="1000000" ISDESCRIPTION="N" LASTPRICESO="12.5" PRICESTD="12.5" />
  <C_ORDERLINE C_ORDERLINE_ID="1000034" AD_CLIENT_ID="1000000" AD_ORG_ID="1000000" ISACTIVE="Y" CREATED="2006-04-03 10:32:29.0" CREATEDBY="100" UPDATED="2006-04-03 11:28:12.0" UPDATEDBY="100" C_ORDER_ID="1000024" LINE="20" C_BPARTNER_ID="1000004" C_BPARTNER_LOCATION_ID="1000001" DATEORDERED="2006-04-03 00:00:00.0" DATEPROMISED="2006-04-03 00:00:00.0" DATEINVOICED="2006-04-03 10:32:50.0" M_PRODUCT_ID="1000004" M_WAREHOUSE_ID="1000000" DIRECTSHIP="N" C_UOM_ID="100" QTYORDERED="5" QTYRESERVED="0" QTYDELIVERED="5" QTYINVOICED="5" C_CURRENCY_ID="102" PRICELIST="13" PRICEACTUAL="12" PRICELIMIT="11" LINENETAMT="60" DISCOUNT="7.69" FREIGHTAMT="0" CHARGEAMT="0" C_TAX_ID="1000000" ISDESCRIPTION="N" PRICESTD="12" />
  <C_ORDERLINE C_ORDERLINE_ID="1000035" AD_CLIENT_ID="1000000" AD_ORG_ID="1000000" ISACTIVE="Y" CREATED="2006-04-03 10:34:20.0" CREATEDBY="100" UPDATED="2006-04-03 10:48:56.0" UPDATEDBY="100" C_ORDER_ID="1000025" LINE="10" C_BPARTNER_ID="1000004" C_BPARTNER_LOCATION_ID="1000001" DATEORDERED="2006-04-03 00:00:00.0" DATEPROMISED="2006-04-03 00:00:00.0" DATEINVOICED="2006-04-03 00:00:00.0" M_PRODUCT_ID="1000005" M_WAREHOUSE_ID="1000000" DIRECTSHIP="N" C_UOM_ID="100" QTYORDERED="7" QTYRESERVED="0" QTYDELIVERED="7" QTYINVOICED="7" C_CURRENCY_ID="102" PRICELIST="42" PRICEACTUAL="37.8" PRICELIMIT="36" LINENETAMT="264.6" DISCOUNT="10" FREIGHTAMT="0" CHARGEAMT="0" C_TAX_ID="1000000" ISDESCRIPTION="N" LASTPRICESO="37.8" PRICESTD="37.8" />
  <C_ORDERLINE C_ORDERLINE_ID="1000036" AD_CLIENT_ID="1000000" AD_ORG_ID="1000000" ISACTIVE="Y" CREATED="2006-04-03 10:56:23.0" CREATEDBY="100" UPDATED="2006-04-03 10:56:44.0" UPDATEDBY="100" C_ORDER_ID="1000026" LINE="10" C_BPARTNER_ID="1000008" C_BPARTNER_LOCATION_ID="1000004" DATEORDERED="2006-04-03 00:00:00.0" DATEPROMISED="2006-04-03 00:00:00.0" M_PRODUCT_ID="1000000" M_WAREHOUSE_ID="1000000" DIRECTSHIP="N" C_UOM_ID="1000001" QTYORDERED="700" QTYRESERVED="0" QTYDELIVERED="0" QTYINVOICED="0" C_CURRENCY_ID="102" PRICELIST="5" PRICEACTUAL="4.6" PRICELIMIT="5.4" LINENETAMT="3220" DISCOUNT="8" FREIGHTAMT="0" CHARGEAMT="0" C_TAX_ID="1000000" ISDESCRIPTION="N" PRICESTD="4.6" />
  <C_ORDERLINE C_ORDERLINE_ID="1000037" AD_CLIENT_ID="1000000" AD_ORG_ID="1000000" ISACTIVE="Y" CREATED="2006-04-03 10:59:42.0" CREATEDBY="100" UPDATED="2006-04-03 11:43:34.0" UPDATEDBY="100" C_ORDER_ID="1000027" LINE="10" C_BPARTNER_ID="1000006" C_BPARTNER_LOCATION_ID="1000011" DATEORDERED="2006-04-03 00:00:00.0" DATEPROMISED="2006-04-03 00:00:00.0" DATEINVOICED="2006-04-03 11:43:24.0" M_PRODUCT_ID="1000000" M_WAREHOUSE_ID="1000000" DIRECTSHIP="N" C_UOM_ID="1000001" QTYORDERED="250" QTYRESERVED="0" QTYDELIVERED="250" QTYINVOICED="250" C_CURRENCY_ID="102" PRICELIST="6.25" PRICEACTUAL="5.9" PRICELIMIT="5.6" LINENETAMT="1475" DISCOUNT="5.6" FREIGHTAMT="0" CHARGEAMT="0" C_TAX_ID="1000000" M_ATTRIBUTESETINSTANCE_ID="1000009" ISDESCRIPTION="N" PRICESTD="5.9" />
  <C_ORDERLINE C_ORDERLINE_ID="1000038" AD_CLIENT_ID="1000000" AD_ORG_ID="1000000" ISACTIVE="Y" CREATED="2006-04-03 11:44:41.0" CREATEDBY="100" UPDATED="2006-04-03 11:53:44.0" UPDATEDBY="100" C_ORDER_ID="1000028" LINE="10" C_BPARTNER_ID="1000006" C_BPARTNER_LOCATION_ID="1000011" DATEORDERED="2006-04-03 00:00:00.0" DATEPROMISED="2006-04-03 00:00:00.0" DATEINVOICED="2006-04-03 11:45:24.0" M_PRODUCT_ID="1000009" M_WAREHOUSE_ID="1000000" DIRECTSHIP="N" C_UOM_ID="100" QTYORDERED="18" QTYRESERVED="0" QTYDELIVERED="18" QTYINVOICED="18" C_CURRENCY_ID="102" PRICELIST="6" PRICEACTUAL="5.8" PRICELIMIT="5.5" LINENETAMT="104.4" DISCOUNT="3.33" FREIGHTAMT="0" CHARGEAMT="0" C_TAX_ID="1000000" ISDESCRIPTION="N" PRICESTD="5.8" />
  <C_ORDERLINE C_ORDERLINE_ID="1000039" AD_CLIENT_ID="1000000" AD_ORG_ID="1000000" ISACTIVE="Y" CREATED="2006-04-07 17:42:15.0" CREATEDBY="100" UPDATED="2006-04-07 17:42:15.0" UPDATEDBY="100" C_ORDER_ID="1000029" LINE="10" C_BPARTNER_ID="1000008" C_BPARTNER_LOCATION_ID="1000004" DATEORDERED="2006-04-07 00:00:00.0" DATEPROMISED="2006-04-07 00:00:00.0" M_PRODUCT_ID="1000004" M_WAREHOUSE_ID="1000000" DIRECTSHIP="N" C_UOM_ID="100" QTYORDERED="2" QTYRESERVED="0" QTYDELIVERED="0" QTYINVOICED="0" C_CURRENCY_ID="102" PRICELIST="10" PRICEACTUAL="9" PRICELIMIT="12" LINENETAMT="18" DISCOUNT="0" FREIGHTAMT="0" CHARGEAMT="0" C_TAX_ID="1000000" ISDESCRIPTION="N" LASTPRICESO="9" PRICESTD="9" />
  <C_ORDERLINE C_ORDERLINE_ID="1000040" AD_CLIENT_ID="1000000" AD_ORG_ID="1000000" ISACTIVE="Y" CREATED="2006-04-07 17:42:31.0" CREATEDBY="100" UPDATED="2006-04-07 17:42:31.0" UPDATEDBY="100" C_ORDER_ID="1000029" LINE="20" C_BPARTNER_ID="1000008" C_BPARTNER_LOCATION_ID="1000004" DATEORDERED="2006-04-07 00:00:00.0" DATEPROMISED="2006-04-07 00:00:00.0" M_PRODUCT_ID="1000009" M_WAREHOUSE_ID="1000000" DIRECTSHIP="N" C_UOM_ID="100" QTYORDERED="1" QTYRESERVED="0" QTYDELIVERED="0" QTYINVOICED="0" C_CURRENCY_ID="102" PRICELIST="5" PRICEACTUAL="4.5" PRICELIMIT="5.4" LINENETAMT="4.5" DISCOUNT="0" FREIGHTAMT="0" CHARGEAMT="0" C_TAX_ID="1000000" ISDESCRIPTION="N" LASTPRICESO="4.5" PRICESTD="4.5" />
  <C_ORDERLINE C_ORDERLINE_ID="1000041" AD_CLIENT_ID="1000000" AD_ORG_ID="1000000" ISACTIVE="Y" CREATED="2006-04-07 17:42:50.0" CREATEDBY="100" UPDATED="2006-04-07 17:42:50.0" UPDATEDBY="100" C_ORDER_ID="1000029" LINE="30" C_BPARTNER_ID="1000008" C_BPARTNER_LOCATION_ID="1000004" DATEORDERED="2006-04-07 00:00:00.0" DATEPROMISED="2006-04-07 00:00:00.0" M_PRODUCT_ID="1000006" M_WAREHOUSE_ID="1000000" DIRECTSHIP="N" C_UOM_ID="100" QTYORDERED="1" QTYRESERVED="0" QTYDELIVERED="0" QTYINVOICED="0" C_CURRENCY_ID="102" PRICELIST="30" PRICEACTUAL="27" PRICELIMIT="34" LINENETAMT="27" DISCOUNT="0" FREIGHTAMT="0" CHARGEAMT="0" C_TAX_ID="1000000" ISDESCRIPTION="N" PRICESTD="27" />
  <C_ORDERLINE C_ORDERLINE_ID="1000042" AD_CLIENT_ID="1000000" AD_ORG_ID="1000000" ISACTIVE="Y" CREATED="2006-04-07 17:55:22.0" CREATEDBY="100" UPDATED="2006-04-07 17:55:22.0" UPDATEDBY="100" C_ORDER_ID="1000030" LINE="10" C_BPARTNER_ID="1000008" C_BPARTNER_LOCATION_ID="1000004" DATEORDERED="2006-04-07 00:00:00.0" DATEPROMISED="2006-04-07 00:00:00.0" M_PRODUCT_ID="1000004" M_WAREHOUSE_ID="1000000" DIRECTSHIP="N" C_UOM_ID="100" QTYORDERED="34" QTYRESERVED="0" QTYDELIVERED="0" QTYINVOICED="0" C_CURRENCY_ID="102" PRICELIST="13" PRICEACTUAL="12" PRICELIMIT="11" LINENETAMT="408" DISCOUNT="0" FREIGHTAMT="0" CHARGEAMT="0" C_TAX_ID="1000000" ISDESCRIPTION="N" LASTPRICESO="9" PRICESTD="12" />
  <C_ORDERLINE C_ORDERLINE_ID="1000043" AD_CLIENT_ID="1000000" AD_ORG_ID="1000000" ISACTIVE="Y" CREATED="2006-04-07 17:55:34.0" CREATEDBY="100" UPDATED="2006-04-07 17:55:34.0" UPDATEDBY="100" C_ORDER_ID="1000030" LINE="20" C_BPARTNER_ID="1000008" C_BPARTNER_LOCATION_ID="1000004" DATEORDERED="2006-04-07 00:00:00.0" DATEPROMISED="2006-04-07 00:00:00.0" M_PRODUCT_ID="1000009" M_WAREHOUSE_ID="1000000" DIRECTSHIP="N" C_UOM_ID="100" QTYORDERED="1" QTYRESERVED="0" QTYDELIVERED="0" QTYINVOICED="0" C_CURRENCY_ID="102" PRICELIST="6" PRICEACTUAL="5.8" PRICELIMIT="5.5" LINENETAMT="5.8" DISCOUNT="0" FREIGHTAMT="0" CHARGEAMT="0" C_TAX_ID="1000000" ISDESCRIPTION="N" LASTPRICESO="4.5" PRICESTD="5.8" />
  <C_ORDERLINE C_ORDERLINE_ID="1000044" AD_CLIENT_ID="1000000" AD_ORG_ID="1000000" ISACTIVE="Y" CREATED="2006-04-12 11:03:29.0" CREATEDBY="100" UPDATED="2006-04-12 11:27:43.0" UPDATEDBY="100" C_ORDER_ID="1000031" LINE="10" C_BPARTNER_ID="1000007" C_BPARTNER_LOCATION_ID="1000003" DATEORDERED="2006-04-12 00:00:00.0" DATEPROMISED="2006-04-12 00:00:00.0" M_PRODUCT_ID="1000028" M_WAREHOUSE_ID="1000000" DIRECTSHIP="N" C_UOM_ID="100" QTYORDERED="240" QTYRESERVED="-240" QTYDELIVERED="0" QTYINVOICED="0" C_CURRENCY_ID="102" PRICELIST="60" PRICEACTUAL="55" PRICELIMIT="70" LINENETAMT="13200" DISCOUNT="8.33" FREIGHTAMT="0" CHARGEAMT="0" C_TAX_ID="1000000" ISDESCRIPTION="N" PRICESTD="55" />
  <C_ORDERLINE C_ORDERLINE_ID="1000045" AD_CLIENT_ID="1000000" AD_ORG_ID="1000000" ISACTIVE="Y" CREATED="2006-04-12 11:06:07.0" CREATEDBY="100" UPDATED="2006-04-12 11:16:03.0" UPDATEDBY="100" C_ORDER_ID="1000032" LINE="10" C_BPARTNER_ID="1000017" C_BPARTNER_LOCATION_ID="1000015" DATEORDERED="2006-04-12 00:00:00.0" DATEPROMISED="2006-04-12 00:00:00.0" M_PRODUCT_ID="1000022" M_WAREHOUSE_ID="1000000" DIRECTSHIP="N" C_UOM_ID="100" QTYORDERED="30" QTYRESERVED="-60" QTYDELIVERED="0" QTYINVOICED="0" C_CURRENCY_ID="102" PRICELIST="180" PRICEACTUAL="175" PRICELIMIT="190" LINENETAMT="5250" DISCOUNT="2.78" FREIGHTAMT="0" CHARGEAMT="0" C_TAX_ID="1000000" ISDESCRIPTION="N" PRICESTD="175" />
  <C_ORDERLINE C_ORDERLINE_ID="1000046" AD_CLIENT_ID="1000000" AD_ORG_ID="1000000" ISACTIVE="Y" CREATED="2006-04-12 11:51:25.0" CREATEDBY="100" UPDATED="2006-04-12 11:52:50.0" UPDATEDBY="100" C_ORDER_ID="1000033" LINE="10" C_BPARTNER_ID="1000008" C_BPARTNER_LOCATION_ID="1000004" DATEORDERED="2006-04-12 00:00:00.0" DATEPROMISED="2006-04-12 00:00:00.0" M_PRODUCT_ID="1000000" M_WAREHOUSE_ID="1000000" DIRECTSHIP="N" C_UOM_ID="1000001" QTYORDERED="3000" QTYRESERVED="-3000" QTYDELIVERED="0" QTYINVOICED="0" C_CURRENCY_ID="102" PRICELIST="5" PRICEACTUAL="4.6" PRICELIMIT="5.4" LINENETAMT="13800" DISCOUNT="8" FREIGHTAMT="0" CHARGEAMT="0" C_TAX_ID="1000000" ISDESCRIPTION="N" LASTPRICESO="4.6" PRICESTD="4.6" />
  <C_ORDERLINE C_ORDERLINE_ID="1000048" AD_CLIENT_ID="1000000" AD_ORG_ID="1000000" ISACTIVE="Y" CREATED="2006-08-07 19:40:55.0" CREATEDBY="100" UPDATED="2006-08-07 19:57:38.0" UPDATEDBY="100" C_ORDER_ID="1000034" LINE="10" C_BPARTNER_ID="1000008" C_BPARTNER_LOCATION_ID="1000004" DATEORDERED="2006-08-07 00:00:00.0" DATEPROMISED="2006-08-07 00:00:00.0" M_PRODUCT_ID="1000008" M_WAREHOUSE_ID="1000000" DIRECTSHIP="N" C_UOM_ID="100" QTYORDERED="300" QTYRESERVED="-300" QTYDELIVERED="0" QTYINVOICED="0" C_CURRENCY_ID="102" PRICELIST="1" PRICEACTUAL="0.95" PRICELIMIT="1.1" LINENETAMT="285" DISCOUNT="5" FREIGHTAMT="0" CHARGEAMT="0" C_TAX_ID="1000000" ISDESCRIPTION="N" PRICESTD="0.95" />
  <C_ORDERLINE C_ORDERLINE_ID="1000049" AD_CLIENT_ID="1000000" AD_ORG_ID="1000000" ISACTIVE="Y" CREATED="2006-08-07 19:42:02.0" CREATEDBY="100" UPDATED="2006-08-07 19:57:38.0" UPDATEDBY="100" C_ORDER_ID="1000034" LINE="20" C_BPARTNER_ID="1000008" C_BPARTNER_LOCATION_ID="1000004" DATEORDERED="2006-08-07 00:00:00.0" DATEPROMISED="2006-08-07 00:00:00.0" M_PRODUCT_ID="1000007" M_WAREHOUSE_ID="1000000" DIRECTSHIP="N" C_UOM_ID="1000002" QTYORDERED="30" QTYRESERVED="-30" QTYDELIVERED="0" QTYINVOICED="0" C_CURRENCY_ID="102" PRICELIST="0.45" PRICEACTUAL="0.42" PRICELIMIT="0.5" LINENETAMT="12.6" DISCOUNT="6.67" FREIGHTAMT="0" CHARGEAMT="0" C_TAX_ID="1000000" ISDESCRIPTION="N" PRICESTD="0.42" />
  <C_ORDERLINE C_ORDERLINE_ID="1000050" AD_CLIENT_ID="1000000" AD_ORG_ID="1000000" ISACTIVE="Y" CREATED="2006-08-08 14:23:42.0" CREATEDBY="100" UPDATED="2006-08-08 14:24:40.0" UPDATEDBY="100" C_ORDER_ID="1000035" LINE="10" C_BPARTNER_ID="1000004" C_BPARTNER_LOCATION_ID="1000001" DATEORDERED="2006-08-08 00:00:00.0" DATEPROMISED="2006-08-08 00:00:00.0" DATEINVOICED="2006-08-08 14:24:22.0" M_PRODUCT_ID="1000011" M_WAREHOUSE_ID="1000000" DIRECTSHIP="N" C_UOM_ID="100" QTYORDERED="5" QTYRESERVED="0" QTYDELIVERED="5" QTYINVOICED="5" C_CURRENCY_ID="102" PRICELIST="13" PRICEACTUAL="12.5" PRICELIMIT="12" LINENETAMT="62.5" DISCOUNT="3.85" FREIGHTAMT="0" CHARGEAMT="0" C_TAX_ID="1000000" ISDESCRIPTION="N" LASTPRICESO="12.5" PRICESTD="12.5" />
  <C_ORDERLINE C_ORDERLINE_ID="1000051" AD_CLIENT_ID="1000000" AD_ORG_ID="1000000" ISACTIVE="Y" CREATED="2006-08-31 16:12:24.0" CREATEDBY="100" UPDATED="2006-08-31 16:21:14.0" UPDATEDBY="100" C_ORDER_ID="1000036" LINE="10" C_BPARTNER_ID="1000006" C_BPARTNER_LOCATION_ID="1000011" DATEORDERED="2006-08-31 00:00:00.0" DATEPROMISED="2006-08-31 00:00:00.0" DATEINVOICED="2006-08-31 16:12:32.0" M_PRODUCT_ID="1000004" M_WAREHOUSE_ID="1000000" DIRECTSHIP="N" C_UOM_ID="100" QTYORDERED="20" QTYRESERVED="0" QTYDELIVERED="20" QTYINVOICED="0" C_CURRENCY_ID="102" PRICELIST="11.7" PRICEACTUAL="10.8" PRICELIMIT="9.9" LINENETAMT="216" DISCOUNT="7.69" FREIGHTAMT="0" CHARGEAMT="0" C_TAX_ID="1000000" ISDESCRIPTION="N" LASTPRICESO="9.94" PRICESTD="10.8" />
  <C_ORDERLINE C_ORDERLINE_ID="1000052" AD_CLIENT_ID="1000000" AD_ORG_ID="1000000" ISACTIVE="Y" CREATED="2006-12-12 12:19:16.0" CREATEDBY="1000000" UPDATED="2006-12-12 12:19:16.0" UPDATEDBY="1000000" C_ORDER_ID="1000038" LINE="10" C_BPARTNER_ID="1000017" C_BPARTNER_LOCATION_ID="1000015" DATEORDERED="2006-12-12 00:00:00.0" DATEPROMISED="2006-12-12 00:00:00.0" M_PRODUCT_ID="1000014" M_WAREHOUSE_ID="1000000" DIRECTSHIP="N" C_UOM_ID="1000002" QTYORDERED="100" QTYRESERVED="0" QTYDELIVERED="0" QTYINVOICED="0" C_CURRENCY_ID="102" PRICELIST="1" PRICEACTUAL="1" PRICELIMIT="1" LINENETAMT="100" DISCOUNT="0" FREIGHTAMT="0" CHARGEAMT="0" C_TAX_ID="1000000" ISDESCRIPTION="N" PRICESTD="1" />
  <C_ORDERLINE C_ORDERLINE_ID="1000053" AD_CLIENT_ID="1000000" AD_ORG_ID="1000000" ISACTIVE="Y" CREATED="2006-12-12 12:19:40.0" CREATEDBY="1000000" UPDATED="2006-12-12 12:19:40.0" UPDATEDBY="1000000" C_ORDER_ID="1000038" LINE="20" C_BPARTNER_ID="1000017" C_BPARTNER_LOCATION_ID="1000015" DATEORDERED="2006-12-12 00:00:00.0" DATEPROMISED="2006-12-12 00:00:00.0" M_PRODUCT_ID="1000008" M_WAREHOUSE_ID="1000000" DIRECTSHIP="N" C_UOM_ID="100" QTYORDERED="50" QTYRESERVED="50" QTYDELIVERED="0" QTYINVOICED="0" C_CURRENCY_ID="102" PRICELIST="2.59" PRICEACTUAL="2.43" PRICELIMIT="2.04" LINENETAMT="121.5" DISCOUNT="0" FREIGHTAMT="0" CHARGEAMT="0" C_TAX_ID="1000000" ISDESCRIPTION="N" LASTPRICESO="2.43" PRICESTD="2.43" />
  <C_ORDERLINE C_ORDERLINE_ID="1000054" AD_CLIENT_ID="1000000" AD_ORG_ID="1000000" ISACTIVE="Y" CREATED="2006-12-12 12:22:12.0" CREATEDBY="1000000" UPDATED="2006-12-12 12:22:12.0" UPDATEDBY="1000000" C_ORDER_ID="1000039" LINE="10" C_BPARTNER_ID="1000010" C_BPARTNER_LOCATION_ID="1000006" DATEORDERED="2006-12-12 00:00:00.0" DATEPROMISED="2006-12-12 00:00:00.0" M_PRODUCT_ID="1000009" M_WAREHOUSE_ID="1000000" DIRECTSHIP="N" C_UOM_ID="100" QTYORDERED="11" QTYRESERVED="11" QTYDELIVERED="0" QTYINVOICED="0" C_CURRENCY_ID="102" PRICELIST="6" PRICEACTUAL="5.8" PRICELIMIT="5.5" LINENETAMT="63.8" DISCOUNT="0" FREIGHTAMT="0" CHARGEAMT="0" C_TAX_ID="1000000" ISDESCRIPTION="N" PRICESTD="5.8" />
  <C_ORDERLINE C_ORDERLINE_ID="1000055" AD_CLIENT_ID="1000000" AD_ORG_ID="1000000" ISACTIVE="Y" CREATED="2006-12-12 12:22:31.0" CREATEDBY="1000000" UPDATED="2006-12-12 12:22:31.0" UPDATEDBY="1000000" C_ORDER_ID="1000039" LINE="20" C_BPARTNER_ID="1000010" C_BPARTNER_LOCATION_ID="1000006" DATEORDERED="2006-12-12 00:00:00.0" DATEPROMISED="2006-12-12 00:00:00.0" M_PRODUCT_ID="1000010" M_WAREHOUSE_ID="1000000" DIRECTSHIP="N" C_UOM_ID="100" QTYORDERED="11" QTYRESERVED="11" QTYDELIVERED="0" QTYINVOICED="0" C_CURRENCY_ID="102" PRICELIST="1.5" PRICEACTUAL="1.45" PRICELIMIT="1.3" LINENETAMT="15.95" DISCOUNT="0" FREIGHTAMT="0" CHARGEAMT="0" C_TAX_ID="1000000" ISDESCRIPTION="N" PRICESTD="1.45" />
  <C_ORDERLINE C_ORDERLINE_ID="1000057" AD_CLIENT_ID="1000000" AD_ORG_ID="1000000" ISACTIVE="Y" CREATED="2007-02-01 21:48:24.0" CREATEDBY="1000000" UPDATED="2007-02-01 21:51:22.0" UPDATEDBY="1000000" C_ORDER_ID="1000042" LINE="10" C_BPARTNER_ID="1000017" C_BPARTNER_LOCATION_ID="1000015" DATEORDERED="2007-02-01 00:00:00.0" DATEPROMISED="2007-02-01 00:00:00.0" DATEINVOICED="2007-02-01 00:00:00.0" DESCRIPTION=" - Phase 1 - " M_PRODUCT_ID="1000029" M_WAREHOUSE_ID="1000000" DIRECTSHIP="N" C_UOM_ID="102" QTYORDERED="1" QTYRESERVED="0" QTYDELIVERED="0" QTYINVOICED="1" C_CURRENCY_ID="102" PRICELIST="3000" PRICEACTUAL="2000" PRICELIMIT="1000" LINENETAMT="2000" DISCOUNT="33.33333333333333333333333333333333333333" FREIGHTAMT="0" CHARGEAMT="0" C_TAX_ID="1000000" ISDESCRIPTION="N" PRICESTD="2000" />
  <C_ORDERLINE C_ORDERLINE_ID="1000058" AD_CLIENT_ID="1000000" AD_ORG_ID="1000000" ISACTIVE="Y" CREATED="2007-02-01 22:04:21.0" CREATEDBY="100" UPDATED="2007-02-01 22:10:51.0" UPDATEDBY="100" C_ORDER_ID="1000043" LINE="10" C_BPARTNER_ID="1000017" C_BPARTNER_LOCATION_ID="1000015" DATEORDERED="2007-02-01 00:00:00.0" DATEPROMISED="2007-02-01 00:00:00.0" DATEINVOICED="2007-02-01 22:08:28.0" M_PRODUCT_ID="1000001" M_WAREHOUSE_ID="1000000" DIRECTSHIP="N" C_UOM_ID="100" QTYORDERED="20.45" QTYRESERVED="0" QTYDELIVERED="20.45" QTYINVOICED="20.45" C_CURRENCY_ID="102" PRICELIST="1" PRICEACTUAL="1" PRICELIMIT="0" LINENETAMT="20.45" DISCOUNT="0" FREIGHTAMT="0" CHARGEAMT="0" C_TAX_ID="1000000" ISDESCRIPTION="N" PRICESTD="1" />
  <C_ORDERLINE C_ORDERLINE_ID="1000059" AD_CLIENT_ID="1000000" AD_ORG_ID="1000000" ISACTIVE="Y" CREATED="2007-02-01 23:36:46.0" CREATEDBY="100" UPDATED="2007-02-01 23:43:36.0" UPDATEDBY="100" C_ORDER_ID="1000044" LINE="10" C_BPARTNER_ID="1000019" C_BPARTNER_LOCATION_ID="1000016" DATEORDERED="2007-02-01 00:00:00.0" DATEPROMISED="2007-02-01 00:00:00.0" DESCRIPTION=" - Consulting phase I - " M_PRODUCT_ID="1000029" M_WAREHOUSE_ID="1000000" DIRECTSHIP="N" C_UOM_ID="102" QTYORDERED="0" QTYRESERVED="0" QTYDELIVERED="0" QTYINVOICED="0" C_CURRENCY_ID="102" PRICELIST="3000" PRICEACTUAL="34" PRICELIMIT="1000" LINENETAMT="0" DISCOUNT="33.33333333333333333333333333333333333333" FREIGHTAMT="0" CHARGEAMT="0" C_TAX_ID="1000000" ISDESCRIPTION="N" PRICESTD="2000" />
  <C_ORDERLINE C_ORDERLINE_ID="1000062" AD_CLIENT_ID="1000000" AD_ORG_ID="1000000" ISACTIVE="Y" CREATED="2007-02-02 00:08:35.0" CREATEDBY="100" UPDATED="2007-02-02 00:08:35.0" UPDATEDBY="100" C_ORDER_ID="1000047" LINE="10" C_BPARTNER_ID="1000008" C_BPARTNER_LOCATION_ID="1000004" DATEORDERED="2007-02-02 00:00:00.0" DATEPROMISED="2007-02-02 00:00:00.0" DESCRIPTION=" - Consulting phase I - " M_PRODUCT_ID="1000007" M_WAREHOUSE_ID="1000000" DIRECTSHIP="N" C_UOM_ID="1000002" QTYORDERED="24" QTYRESERVED="24" QTYDELIVERED="0" QTYINVOICED="0" C_CURRENCY_ID="102" PRICELIST="0.63" PRICEACTUAL="0.6" PRICELIMIT="0.55" LINENETAMT="14.4" DISCOUNT="4.76190476190476190476190476190476190476" FREIGHTAMT="0" CHARGEAMT="0" C_TAX_ID="1000000" ISDESCRIPTION="N" PRICESTD="0.6" />
  <C_ORDERLINE C_ORDERLINE_ID="1000065" AD_CLIENT_ID="1000000" AD_ORG_ID="1000000" ISACTIVE="Y" CREATED="2007-02-02 00:30:47.0" CREATEDBY="100" UPDATED="2007-02-02 00:30:50.0" UPDATEDBY="100" C_ORDER_ID="1000050" LINE="10" C_BPARTNER_ID="1000019" C_BPARTNER_LOCATION_ID="1000016" DATEORDERED="2007-02-02 00:00:00.0" DATEPROMISED="2007-02-02 00:00:00.0" M_PRODUCT_ID="1000030" M_WAREHOUSE_ID="1000000" DIRECTSHIP="N" C_UOM_ID="100" QTYORDERED="4" QTYRESERVED="0" QTYDELIVERED="4" QTYINVOICED="0" C_CURRENCY_ID="102" PRICELIST="0" PRICEACTUAL="123" PRICELIMIT="0" LINENETAMT="492" FREIGHTAMT="0" CHARGEAMT="0" C_TAX_ID="1000000" ISDESCRIPTION="N" PRICESTD="123" />
</data>
