<?xml version='1.0' encoding='UTF-8'?>
<data>
<!--
************************
0. Core Range.
************************
-->
<!--
************************
0. End of Core Range.
************************
-->
<!--
************************
1. Custom Range.
************************
-->
<!--M_PRODUCTION_ID=1000003-->                    <M_PRODUCTION>
<!--M_PRODUCTION_ID=1000003 M_PRODUCTION_ID-->
<!--M_PRODUCTION_ID=1000003-->                        <M_PRODUCTION_ID><![CDATA[1000003]]></M_PRODUCTION_ID>
<!--M_PRODUCTION_ID=1000003 AD_CLIENT_ID-->
<!--M_PRODUCTION_ID=1000003-->                        <AD_CLIENT_ID><![CDATA[1000000]]></AD_CLIENT_ID>
<!--M_PRODUCTION_ID=1000003 AD_ORG_ID-->
<!--M_PRODUCTION_ID=1000003-->                        <AD_ORG_ID><![CDATA[1000000]]></AD_ORG_ID>
<!--M_PRODUCTION_ID=1000003 ISACTIVE-->
<!--M_PRODUCTION_ID=1000003-->                        <ISACTIVE><![CDATA[Y]]></ISACTIVE>
<!--M_PRODUCTION_ID=1000003 CREATED-->
<!--M_PRODUCTION_ID=1000003-->                        <CREATED><![CDATA[2006-03-29 13:16:11.0]]></CREATED>
<!--M_PRODUCTION_ID=1000003 CREATEDBY-->
<!--M_PRODUCTION_ID=1000003-->                        <CREATEDBY><![CDATA[100]]></CREATEDBY>
<!--M_PRODUCTION_ID=1000003 UPDATED-->
<!--M_PRODUCTION_ID=1000003-->                        <UPDATED><![CDATA[2006-03-29 13:17:20.0]]></UPDATED>
<!--M_PRODUCTION_ID=1000003 UPDATEDBY-->
<!--M_PRODUCTION_ID=1000003-->                        <UPDATEDBY><![CDATA[100]]></UPDATEDBY>
<!--M_PRODUCTION_ID=1000003 NAME-->
<!--M_PRODUCTION_ID=1000003-->                        <NAME><![CDATA[Homer Kits 29-03-2006]]></NAME>
<!--M_PRODUCTION_ID=1000003 MOVEMENTDATE-->
<!--M_PRODUCTION_ID=1000003-->                        <MOVEMENTDATE><![CDATA[2006-03-29 00:00:00.0]]></MOVEMENTDATE>
<!--M_PRODUCTION_ID=1000003 ISCREATED-->
<!--M_PRODUCTION_ID=1000003-->                        <ISCREATED><![CDATA[Y]]></ISCREATED>
<!--M_PRODUCTION_ID=1000003 POSTED-->
<!--M_PRODUCTION_ID=1000003-->                        <POSTED><![CDATA[N]]></POSTED>
<!--M_PRODUCTION_ID=1000003 PROCESSED-->
<!--M_PRODUCTION_ID=1000003-->                        <PROCESSED><![CDATA[Y]]></PROCESSED>
<!--M_PRODUCTION_ID=1000003 PROCESSING-->
<!--M_PRODUCTION_ID=1000003-->                        <PROCESSING><![CDATA[N]]></PROCESSING>
<!--M_PRODUCTION_ID=1000003 ISSOTRX-->
<!--M_PRODUCTION_ID=1000003-->                        <ISSOTRX><![CDATA[Y]]></ISSOTRX>
<!--M_PRODUCTION_ID=1000003-->                    </M_PRODUCTION>
<!--M_PRODUCTION_ID=1000006-->                    <M_PRODUCTION>
<!--M_PRODUCTION_ID=1000006 M_PRODUCTION_ID-->
<!--M_PRODUCTION_ID=1000006-->                        <M_PRODUCTION_ID><![CDATA[1000006]]></M_PRODUCTION_ID>
<!--M_PRODUCTION_ID=1000006 AD_CLIENT_ID-->
<!--M_PRODUCTION_ID=1000006-->                        <AD_CLIENT_ID><![CDATA[1000000]]></AD_CLIENT_ID>
<!--M_PRODUCTION_ID=1000006 AD_ORG_ID-->
<!--M_PRODUCTION_ID=1000006-->                        <AD_ORG_ID><![CDATA[1000000]]></AD_ORG_ID>
<!--M_PRODUCTION_ID=1000006 ISACTIVE-->
<!--M_PRODUCTION_ID=1000006-->                        <ISACTIVE><![CDATA[Y]]></ISACTIVE>
<!--M_PRODUCTION_ID=1000006 CREATED-->
<!--M_PRODUCTION_ID=1000006-->                        <CREATED><![CDATA[2006-08-07 21:37:41.0]]></CREATED>
<!--M_PRODUCTION_ID=1000006 CREATEDBY-->
<!--M_PRODUCTION_ID=1000006-->                        <CREATEDBY><![CDATA[100]]></CREATEDBY>
<!--M_PRODUCTION_ID=1000006 UPDATED-->
<!--M_PRODUCTION_ID=1000006-->                        <UPDATED><![CDATA[2006-08-07 21:37:41.0]]></UPDATED>
<!--M_PRODUCTION_ID=1000006 UPDATEDBY-->
<!--M_PRODUCTION_ID=1000006-->                        <UPDATEDBY><![CDATA[100]]></UPDATEDBY>
<!--M_PRODUCTION_ID=1000006 NAME-->
<!--M_PRODUCTION_ID=1000006-->                        <NAME><![CDATA[prod 07-08-2006]]></NAME>
<!--M_PRODUCTION_ID=1000006 MOVEMENTDATE-->
<!--M_PRODUCTION_ID=1000006-->                        <MOVEMENTDATE><![CDATA[2006-08-07 00:00:00.0]]></MOVEMENTDATE>
<!--M_PRODUCTION_ID=1000006 ISCREATED-->
<!--M_PRODUCTION_ID=1000006-->                        <ISCREATED><![CDATA[Y]]></ISCREATED>
<!--M_PRODUCTION_ID=1000006 POSTED-->
<!--M_PRODUCTION_ID=1000006-->                        <POSTED><![CDATA[N]]></POSTED>
<!--M_PRODUCTION_ID=1000006 PROCESSED-->
<!--M_PRODUCTION_ID=1000006-->                        <PROCESSED><![CDATA[N]]></PROCESSED>
<!--M_PRODUCTION_ID=1000006 PROCESSING-->
<!--M_PRODUCTION_ID=1000006-->                        <PROCESSING><![CDATA[N]]></PROCESSING>
<!--M_PRODUCTION_ID=1000006 ISSOTRX-->
<!--M_PRODUCTION_ID=1000006-->                        <ISSOTRX><![CDATA[Y]]></ISSOTRX>
<!--M_PRODUCTION_ID=1000006-->                    </M_PRODUCTION>
<!--
************************
1. End of Custom Range.
************************
-->
</data>
